[ {
  "@id" : "_:genid1",
  "@type" : [ "http://www.w3.org/2002/07/owl#Class" ],
  "http://www.w3.org/2002/07/owl#unionOf" : [ {
    "@list" : [ {
      "@id" : "http://precis.rukmal.me/ontology#Accolade"
    }, {
      "@id" : "http://precis.rukmal.me/ontology#Portfolio"
    } ]
  } ]
}, {
  "@id" : "_:genid100",
  "@type" : [ "http://www.w3.org/2002/07/owl#Class" ],
  "http://www.w3.org/2002/07/owl#unionOf" : [ {
    "@list" : [ {
      "@id" : "http://precis.rukmal.me/ontology#Accolade"
    }, {
      "@id" : "http://precis.rukmal.me/ontology#ActivityType"
    }, {
      "@id" : "http://precis.rukmal.me/ontology#Course"
    }, {
      "@id" : "http://precis.rukmal.me/ontology#Organization"
    }, {
      "@id" : "http://precis.rukmal.me/ontology#Portfolio"
    }, {
      "@id" : "http://precis.rukmal.me/ontology#SkillGroup"
    }, {
      "@id" : "http://precis.rukmal.me/ontology#WorkExperience"
    } ]
  } ]
}, {
  "@id" : "_:genid108",
  "@type" : [ "http://www.w3.org/2002/07/owl#Class" ],
  "http://www.w3.org/2002/07/owl#unionOf" : [ {
    "@list" : [ {
      "@id" : "http://precis.rukmal.me/ontology#Accolade"
    }, {
      "@id" : "http://precis.rukmal.me/ontology#ActivityType"
    }, {
      "@id" : "http://precis.rukmal.me/ontology#Course"
    }, {
      "@id" : "http://precis.rukmal.me/ontology#Degree"
    }, {
      "@id" : "http://precis.rukmal.me/ontology#Organization"
    }, {
      "@id" : "http://precis.rukmal.me/ontology#Portfolio"
    }, {
      "@id" : "http://precis.rukmal.me/ontology#SkillGroup"
    }, {
      "@id" : "http://precis.rukmal.me/ontology#WorkExperience"
    } ]
  } ]
}, {
  "@id" : "_:genid117",
  "@type" : [ "http://www.w3.org/2000/01/rdf-schema#Datatype" ],
  "http://www.w3.org/2002/07/owl#onDatatype" : [ {
    "@id" : "http://www.w3.org/2001/XMLSchema#double"
  } ],
  "http://www.w3.org/2002/07/owl#withRestrictions" : [ {
    "@list" : [ {
      "@id" : "_:genid121"
    }, {
      "@id" : "_:genid119"
    } ]
  } ]
}, {
  "@id" : "_:genid119",
  "http://www.w3.org/2001/XMLSchema#maxInclusive" : [ {
    "@type" : "http://www.w3.org/2001/XMLSchema#double",
    "@value" : "4.0"
  } ]
}, {
  "@id" : "_:genid121",
  "http://www.w3.org/2001/XMLSchema#minInclusive" : [ {
    "@type" : "http://www.w3.org/2001/XMLSchema#double",
    "@value" : "0.0"
  } ]
}, {
  "@id" : "_:genid122",
  "@type" : [ "http://www.w3.org/2002/07/owl#Restriction" ],
  "http://www.w3.org/2002/07/owl#onProperty" : [ {
    "@id" : "http://precis.rukmal.me/ontology#affiliatedWith"
  } ],
  "http://www.w3.org/2002/07/owl#someValuesFrom" : [ {
    "@id" : "_:genid123"
  } ]
}, {
  "@id" : "_:genid123",
  "@type" : [ "http://www.w3.org/2002/07/owl#Class" ],
  "http://www.w3.org/2002/07/owl#unionOf" : [ {
    "@list" : [ {
      "@id" : "http://precis.rukmal.me/ontology#Degree"
    }, {
      "@id" : "http://precis.rukmal.me/ontology#WorkExperience"
    } ]
  } ]
}, {
  "@id" : "_:genid126",
  "@type" : [ "http://www.w3.org/2002/07/owl#Restriction" ],
  "http://www.w3.org/2002/07/owl#minQualifiedCardinality" : [ {
    "@type" : "http://www.w3.org/2001/XMLSchema#nonNegativeInteger",
    "@value" : "1"
  } ],
  "http://www.w3.org/2002/07/owl#onClass" : [ {
    "@id" : "http://precis.rukmal.me/ontology#Description"
  } ],
  "http://www.w3.org/2002/07/owl#onProperty" : [ {
    "@id" : "http://precis.rukmal.me/ontology#hasDescription"
  } ]
}, {
  "@id" : "_:genid127",
  "@type" : [ "http://www.w3.org/2002/07/owl#Restriction" ],
  "http://www.w3.org/2002/07/owl#onProperty" : [ {
    "@id" : "http://precis.rukmal.me/ontology#externalResource"
  } ],
  "http://www.w3.org/2002/07/owl#someValuesFrom" : [ {
    "@id" : "http://www.w3.org/2001/XMLSchema#anyURI"
  } ]
}, {
  "@id" : "_:genid128",
  "@type" : [ "http://www.w3.org/2002/07/owl#Restriction" ],
  "http://www.w3.org/2002/07/owl#onProperty" : [ {
    "@id" : "http://precis.rukmal.me/ontology#hasMedia"
  } ],
  "http://www.w3.org/2002/07/owl#someValuesFrom" : [ {
    "@id" : "http://www.w3.org/2001/XMLSchema#anyURI"
  } ]
}, {
  "@id" : "_:genid129",
  "@type" : [ "http://www.w3.org/2002/07/owl#Restriction" ],
  "http://www.w3.org/2002/07/owl#minQualifiedCardinality" : [ {
    "@type" : "http://www.w3.org/2001/XMLSchema#nonNegativeInteger",
    "@value" : "1"
  } ],
  "http://www.w3.org/2002/07/owl#onDataRange" : [ {
    "@id" : "http://www.w3.org/2001/XMLSchema#dateTime"
  } ],
  "http://www.w3.org/2002/07/owl#onProperty" : [ {
    "@id" : "http://precis.rukmal.me/ontology#hasDate"
  } ]
}, {
  "@id" : "_:genid130",
  "@type" : [ "http://www.w3.org/2002/07/owl#Restriction" ],
  "http://www.w3.org/2002/07/owl#onDataRange" : [ {
    "@id" : "http://www.w3.org/2001/XMLSchema#string"
  } ],
  "http://www.w3.org/2002/07/owl#onProperty" : [ {
    "@id" : "http://precis.rukmal.me/ontology#hasName"
  } ],
  "http://www.w3.org/2002/07/owl#qualifiedCardinality" : [ {
    "@type" : "http://www.w3.org/2001/XMLSchema#nonNegativeInteger",
    "@value" : "1"
  } ]
}, {
  "@id" : "_:genid131",
  "@type" : [ "http://www.w3.org/2002/07/owl#Restriction" ],
  "http://www.w3.org/2002/07/owl#minQualifiedCardinality" : [ {
    "@type" : "http://www.w3.org/2001/XMLSchema#nonNegativeInteger",
    "@value" : "1"
  } ],
  "http://www.w3.org/2002/07/owl#onClass" : [ {
    "@id" : "http://precis.rukmal.me/ontology#ActivityType"
  } ],
  "http://www.w3.org/2002/07/owl#onProperty" : [ {
    "@id" : "http://precis.rukmal.me/ontology#inActivityType"
  } ]
}, {
  "@id" : "_:genid132",
  "@type" : [ "http://www.w3.org/2002/07/owl#Restriction" ],
  "http://www.w3.org/2002/07/owl#minQualifiedCardinality" : [ {
    "@type" : "http://www.w3.org/2001/XMLSchema#nonNegativeInteger",
    "@value" : "1"
  } ],
  "http://www.w3.org/2002/07/owl#onClass" : [ {
    "@id" : "http://precis.rukmal.me/ontology#Activity"
  } ],
  "http://www.w3.org/2002/07/owl#onProperty" : [ {
    "@id" : "http://precis.rukmal.me/ontology#hasActivity"
  } ]
}, {
  "@id" : "_:genid133",
  "@type" : [ "http://www.w3.org/2002/07/owl#Restriction" ],
  "http://www.w3.org/2002/07/owl#minQualifiedCardinality" : [ {
    "@type" : "http://www.w3.org/2001/XMLSchema#nonNegativeInteger",
    "@value" : "1"
  } ],
  "http://www.w3.org/2002/07/owl#onClass" : [ {
    "@id" : "http://precis.rukmal.me/ontology#Description"
  } ],
  "http://www.w3.org/2002/07/owl#onProperty" : [ {
    "@id" : "http://precis.rukmal.me/ontology#hasDescription"
  } ]
}, {
  "@id" : "_:genid134",
  "@type" : [ "http://www.w3.org/2002/07/owl#Restriction" ],
  "http://www.w3.org/2002/07/owl#onProperty" : [ {
    "@id" : "http://precis.rukmal.me/ontology#endDate"
  } ],
  "http://www.w3.org/2002/07/owl#someValuesFrom" : [ {
    "@id" : "http://www.w3.org/2001/XMLSchema#dateTime"
  } ]
}, {
  "@id" : "_:genid135",
  "@type" : [ "http://www.w3.org/2002/07/owl#Restriction" ],
  "http://www.w3.org/2002/07/owl#onProperty" : [ {
    "@id" : "http://precis.rukmal.me/ontology#externalResource"
  } ],
  "http://www.w3.org/2002/07/owl#someValuesFrom" : [ {
    "@id" : "http://www.w3.org/2001/XMLSchema#anyURI"
  } ]
}, {
  "@id" : "_:genid136",
  "@type" : [ "http://www.w3.org/2002/07/owl#Restriction" ],
  "http://www.w3.org/2002/07/owl#onProperty" : [ {
    "@id" : "http://precis.rukmal.me/ontology#hasDate"
  } ],
  "http://www.w3.org/2002/07/owl#someValuesFrom" : [ {
    "@id" : "http://www.w3.org/2001/XMLSchema#dateTime"
  } ]
}, {
  "@id" : "_:genid137",
  "@type" : [ "http://www.w3.org/2002/07/owl#Restriction" ],
  "http://www.w3.org/2002/07/owl#onProperty" : [ {
    "@id" : "http://precis.rukmal.me/ontology#hasMedia"
  } ],
  "http://www.w3.org/2002/07/owl#someValuesFrom" : [ {
    "@id" : "http://www.w3.org/2001/XMLSchema#anyURI"
  } ]
}, {
  "@id" : "_:genid138",
  "@type" : [ "http://www.w3.org/2002/07/owl#Restriction" ],
  "http://www.w3.org/2002/07/owl#onDataRange" : [ {
    "@id" : "http://www.w3.org/2001/XMLSchema#string"
  } ],
  "http://www.w3.org/2002/07/owl#onProperty" : [ {
    "@id" : "http://precis.rukmal.me/ontology#hasName"
  } ],
  "http://www.w3.org/2002/07/owl#qualifiedCardinality" : [ {
    "@type" : "http://www.w3.org/2001/XMLSchema#nonNegativeInteger",
    "@value" : "1"
  } ]
}, {
  "@id" : "_:genid139",
  "@type" : [ "http://www.w3.org/2002/07/owl#Restriction" ],
  "http://www.w3.org/2002/07/owl#onProperty" : [ {
    "@id" : "http://precis.rukmal.me/ontology#hasDescription"
  } ],
  "http://www.w3.org/2002/07/owl#someValuesFrom" : [ {
    "@id" : "http://precis.rukmal.me/ontology#Description"
  } ]
}, {
  "@id" : "_:genid140",
  "@type" : [ "http://www.w3.org/2002/07/owl#Restriction" ],
  "http://www.w3.org/2002/07/owl#onProperty" : [ {
    "@id" : "http://precis.rukmal.me/ontology#taughtAt"
  } ],
  "http://www.w3.org/2002/07/owl#someValuesFrom" : [ {
    "@id" : "http://precis.rukmal.me/ontology#Organization"
  } ]
}, {
  "@id" : "_:genid141",
  "@type" : [ "http://www.w3.org/2002/07/owl#Restriction" ],
  "http://www.w3.org/2002/07/owl#onProperty" : [ {
    "@id" : "http://precis.rukmal.me/ontology#endDate"
  } ],
  "http://www.w3.org/2002/07/owl#someValuesFrom" : [ {
    "@id" : "http://www.w3.org/2001/XMLSchema#dateTime"
  } ]
}, {
  "@id" : "_:genid142",
  "@type" : [ "http://www.w3.org/2002/07/owl#Restriction" ],
  "http://www.w3.org/2002/07/owl#onProperty" : [ {
    "@id" : "http://precis.rukmal.me/ontology#hasCourseCode"
  } ],
  "http://www.w3.org/2002/07/owl#someValuesFrom" : [ {
    "@id" : "http://www.w3.org/2001/XMLSchema#string"
  } ]
}, {
  "@id" : "_:genid143",
  "@type" : [ "http://www.w3.org/2002/07/owl#Restriction" ],
  "http://www.w3.org/2002/07/owl#onProperty" : [ {
    "@id" : "http://precis.rukmal.me/ontology#hasDate"
  } ],
  "http://www.w3.org/2002/07/owl#someValuesFrom" : [ {
    "@id" : "http://www.w3.org/2001/XMLSchema#dateTime"
  } ]
}, {
  "@id" : "_:genid144",
  "@type" : [ "http://www.w3.org/2002/07/owl#Restriction" ],
  "http://www.w3.org/2002/07/owl#onProperty" : [ {
    "@id" : "http://precis.rukmal.me/ontology#hasDepartmentCode"
  } ],
  "http://www.w3.org/2002/07/owl#someValuesFrom" : [ {
    "@id" : "http://www.w3.org/2001/XMLSchema#string"
  } ]
}, {
  "@id" : "_:genid145",
  "@type" : [ "http://www.w3.org/2002/07/owl#Restriction" ],
  "http://www.w3.org/2002/07/owl#onProperty" : [ {
    "@id" : "http://precis.rukmal.me/ontology#withGrade"
  } ],
  "http://www.w3.org/2002/07/owl#someValuesFrom" : [ {
    "@id" : "http://www.w3.org/2001/XMLSchema#double"
  } ]
}, {
  "@id" : "_:genid146",
  "@type" : [ "http://www.w3.org/2002/07/owl#Restriction" ],
  "http://www.w3.org/2002/07/owl#onDataRange" : [ {
    "@id" : "http://www.w3.org/2001/XMLSchema#string"
  } ],
  "http://www.w3.org/2002/07/owl#onProperty" : [ {
    "@id" : "http://precis.rukmal.me/ontology#hasName"
  } ],
  "http://www.w3.org/2002/07/owl#qualifiedCardinality" : [ {
    "@type" : "http://www.w3.org/2001/XMLSchema#nonNegativeInteger",
    "@value" : "1"
  } ]
}, {
  "@id" : "_:genid147",
  "@type" : [ "http://www.w3.org/2002/07/owl#Restriction" ],
  "http://www.w3.org/2002/07/owl#onDataRange" : [ {
    "@id" : "http://www.w3.org/2001/XMLSchema#anyURI"
  } ],
  "http://www.w3.org/2002/07/owl#onProperty" : [ {
    "@id" : "http://precis.rukmal.me/ontology#hasWebsite"
  } ],
  "http://www.w3.org/2002/07/owl#qualifiedCardinality" : [ {
    "@type" : "http://www.w3.org/2001/XMLSchema#nonNegativeInteger",
    "@value" : "1"
  } ]
}, {
  "@id" : "_:genid148",
  "@type" : [ "http://www.w3.org/2002/07/owl#Restriction" ],
  "http://www.w3.org/2002/07/owl#onProperty" : [ {
    "@id" : "http://precis.rukmal.me/ontology#degreeDepartment"
  } ],
  "http://www.w3.org/2002/07/owl#someValuesFrom" : [ {
    "@id" : "http://precis.rukmal.me/ontology#Organization"
  } ]
}, {
  "@id" : "_:genid149",
  "@type" : [ "http://www.w3.org/2002/07/owl#Restriction" ],
  "http://www.w3.org/2002/07/owl#onProperty" : [ {
    "@id" : "http://precis.rukmal.me/ontology#degreeSchool"
  } ],
  "http://www.w3.org/2002/07/owl#someValuesFrom" : [ {
    "@id" : "http://precis.rukmal.me/ontology#Organization"
  } ]
}, {
  "@id" : "_:genid150",
  "@type" : [ "http://www.w3.org/2002/07/owl#Restriction" ],
  "http://www.w3.org/2002/07/owl#minQualifiedCardinality" : [ {
    "@type" : "http://www.w3.org/2001/XMLSchema#nonNegativeInteger",
    "@value" : "1"
  } ],
  "http://www.w3.org/2002/07/owl#onClass" : [ {
    "@id" : "http://precis.rukmal.me/ontology#Organization"
  } ],
  "http://www.w3.org/2002/07/owl#onProperty" : [ {
    "@id" : "http://precis.rukmal.me/ontology#degreeUniversity"
  } ]
}, {
  "@id" : "_:genid151",
  "@type" : [ "http://www.w3.org/2002/07/owl#Restriction" ],
  "http://www.w3.org/2002/07/owl#onProperty" : [ {
    "@id" : "http://precis.rukmal.me/ontology#degreeConcentration"
  } ],
  "http://www.w3.org/2002/07/owl#someValuesFrom" : [ {
    "@id" : "http://www.w3.org/2001/XMLSchema#anyURI"
  } ]
}, {
  "@id" : "_:genid152",
  "@type" : [ "http://www.w3.org/2002/07/owl#Restriction" ],
  "http://www.w3.org/2002/07/owl#onProperty" : [ {
    "@id" : "http://precis.rukmal.me/ontology#degreeGPA"
  } ],
  "http://www.w3.org/2002/07/owl#someValuesFrom" : [ {
    "@id" : "http://www.w3.org/2001/XMLSchema#double"
  } ]
}, {
  "@id" : "_:genid153",
  "@type" : [ "http://www.w3.org/2002/07/owl#Restriction" ],
  "http://www.w3.org/2002/07/owl#onProperty" : [ {
    "@id" : "http://precis.rukmal.me/ontology#degreeType"
  } ],
  "http://www.w3.org/2002/07/owl#someValuesFrom" : [ {
    "@id" : "http://www.w3.org/2001/XMLSchema#anyURI"
  } ]
}, {
  "@id" : "_:genid154",
  "@type" : [ "http://www.w3.org/2002/07/owl#Restriction" ],
  "http://www.w3.org/2002/07/owl#onDataRange" : [ {
    "@id" : "http://www.w3.org/2001/XMLSchema#dateTime"
  } ],
  "http://www.w3.org/2002/07/owl#onProperty" : [ {
    "@id" : "http://precis.rukmal.me/ontology#hasDate"
  } ],
  "http://www.w3.org/2002/07/owl#qualifiedCardinality" : [ {
    "@type" : "http://www.w3.org/2001/XMLSchema#nonNegativeInteger",
    "@value" : "1"
  } ]
}, {
  "@id" : "_:genid155",
  "@type" : [ "http://www.w3.org/2002/07/owl#Restriction" ],
  "http://www.w3.org/2002/07/owl#onDataRange" : [ {
    "@id" : "http://www.w3.org/2001/XMLSchema#string"
  } ],
  "http://www.w3.org/2002/07/owl#onProperty" : [ {
    "@id" : "http://precis.rukmal.me/ontology#hasName"
  } ],
  "http://www.w3.org/2002/07/owl#qualifiedCardinality" : [ {
    "@type" : "http://www.w3.org/2001/XMLSchema#nonNegativeInteger",
    "@value" : "1"
  } ]
}, {
  "@id" : "_:genid156",
  "@type" : [ "http://www.w3.org/2002/07/owl#Restriction" ],
  "http://www.w3.org/2002/07/owl#onDataRange" : [ {
    "@id" : "http://www.w3.org/2001/XMLSchema#string"
  } ],
  "http://www.w3.org/2002/07/owl#onProperty" : [ {
    "@id" : "http://precis.rukmal.me/ontology#inCity"
  } ],
  "http://www.w3.org/2002/07/owl#qualifiedCardinality" : [ {
    "@type" : "http://www.w3.org/2001/XMLSchema#nonNegativeInteger",
    "@value" : "1"
  } ]
}, {
  "@id" : "_:genid157",
  "@type" : [ "http://www.w3.org/2002/07/owl#Restriction" ],
  "http://www.w3.org/2002/07/owl#onDataRange" : [ {
    "@id" : "http://www.w3.org/2001/XMLSchema#string"
  } ],
  "http://www.w3.org/2002/07/owl#onProperty" : [ {
    "@id" : "http://precis.rukmal.me/ontology#inState"
  } ],
  "http://www.w3.org/2002/07/owl#qualifiedCardinality" : [ {
    "@type" : "http://www.w3.org/2001/XMLSchema#nonNegativeInteger",
    "@value" : "1"
  } ]
}, {
  "@id" : "_:genid158",
  "@type" : [ "http://www.w3.org/2002/07/owl#Restriction" ],
  "http://www.w3.org/2002/07/owl#onDataRange" : [ {
    "@id" : "http://www.w3.org/2001/XMLSchema#string"
  } ],
  "http://www.w3.org/2002/07/owl#onProperty" : [ {
    "@id" : "http://precis.rukmal.me/ontology#hasText"
  } ],
  "http://www.w3.org/2002/07/owl#qualifiedCardinality" : [ {
    "@type" : "http://www.w3.org/2001/XMLSchema#nonNegativeInteger",
    "@value" : "1"
  } ]
}, {
  "@id" : "_:genid159",
  "@type" : [ "http://www.w3.org/2002/07/owl#Restriction" ],
  "http://www.w3.org/2002/07/owl#maxQualifiedCardinality" : [ {
    "@type" : "http://www.w3.org/2001/XMLSchema#nonNegativeInteger",
    "@value" : "1"
  } ],
  "http://www.w3.org/2002/07/owl#onDataRange" : [ {
    "@id" : "http://www.w3.org/2001/XMLSchema#nonNegativeInteger"
  } ],
  "http://www.w3.org/2002/07/owl#onProperty" : [ {
    "@id" : "http://precis.rukmal.me/ontology#hasPriority"
  } ]
}, {
  "@id" : "_:genid16",
  "@type" : [ "http://www.w3.org/2002/07/owl#Class" ],
  "http://www.w3.org/2002/07/owl#unionOf" : [ {
    "@list" : [ {
      "@id" : "http://precis.rukmal.me/ontology#Degree"
    }, {
      "@id" : "http://precis.rukmal.me/ontology#WorkExperience"
    } ]
  } ]
}, {
  "@id" : "_:genid160",
  "@type" : [ "http://www.w3.org/2002/07/owl#Restriction" ],
  "http://www.w3.org/2002/07/owl#minQualifiedCardinality" : [ {
    "@type" : "http://www.w3.org/2001/XMLSchema#nonNegativeInteger",
    "@value" : "1"
  } ],
  "http://www.w3.org/2002/07/owl#onClass" : [ {
    "@id" : "http://precis.rukmal.me/ontology#Description"
  } ],
  "http://www.w3.org/2002/07/owl#onProperty" : [ {
    "@id" : "http://precis.rukmal.me/ontology#hasDescription"
  } ]
}, {
  "@id" : "_:genid161",
  "@type" : [ "http://www.w3.org/2002/07/owl#Restriction" ],
  "http://www.w3.org/2002/07/owl#minQualifiedCardinality" : [ {
    "@type" : "http://www.w3.org/2001/XMLSchema#nonNegativeInteger",
    "@value" : "1"
  } ],
  "http://www.w3.org/2002/07/owl#onClass" : [ {
    "@id" : "http://precis.rukmal.me/ontology#Subject"
  } ],
  "http://www.w3.org/2002/07/owl#onProperty" : [ {
    "@id" : "http://precis.rukmal.me/ontology#hasSubject"
  } ]
}, {
  "@id" : "_:genid162",
  "@type" : [ "http://www.w3.org/2002/07/owl#Restriction" ],
  "http://www.w3.org/2002/07/owl#minQualifiedCardinality" : [ {
    "@type" : "http://www.w3.org/2001/XMLSchema#nonNegativeInteger",
    "@value" : "1"
  } ],
  "http://www.w3.org/2002/07/owl#onDataRange" : [ {
    "@id" : "http://www.w3.org/2001/XMLSchema#anyURI"
  } ],
  "http://www.w3.org/2002/07/owl#onProperty" : [ {
    "@id" : "http://precis.rukmal.me/ontology#externalResource"
  } ]
}, {
  "@id" : "_:genid163",
  "@type" : [ "http://www.w3.org/2002/07/owl#Restriction" ],
  "http://www.w3.org/2002/07/owl#onDataRange" : [ {
    "@id" : "http://www.w3.org/2001/XMLSchema#string"
  } ],
  "http://www.w3.org/2002/07/owl#onProperty" : [ {
    "@id" : "http://precis.rukmal.me/ontology#hasName"
  } ],
  "http://www.w3.org/2002/07/owl#qualifiedCardinality" : [ {
    "@type" : "http://www.w3.org/2001/XMLSchema#nonNegativeInteger",
    "@value" : "1"
  } ]
}, {
  "@id" : "_:genid164",
  "@type" : [ "http://www.w3.org/2002/07/owl#Restriction" ],
  "http://www.w3.org/2002/07/owl#onProperty" : [ {
    "@id" : "http://precis.rukmal.me/ontology#hasParentOrganization"
  } ],
  "http://www.w3.org/2002/07/owl#someValuesFrom" : [ {
    "@id" : "http://precis.rukmal.me/ontology#Organization"
  } ]
}, {
  "@id" : "_:genid165",
  "@type" : [ "http://www.w3.org/2002/07/owl#Restriction" ],
  "http://www.w3.org/2002/07/owl#maxQualifiedCardinality" : [ {
    "@type" : "http://www.w3.org/2001/XMLSchema#nonNegativeInteger",
    "@value" : "1"
  } ],
  "http://www.w3.org/2002/07/owl#onClass" : [ {
    "@id" : "http://precis.rukmal.me/ontology#Description"
  } ],
  "http://www.w3.org/2002/07/owl#onProperty" : [ {
    "@id" : "http://precis.rukmal.me/ontology#hasDescription"
  } ]
}, {
  "@id" : "_:genid166",
  "@type" : [ "http://www.w3.org/2002/07/owl#Axiom" ],
  "http://www.w3.org/2000/01/rdf-schema#comment" : [ {
    "@value" : "This should be used to add an additional descriptive string if necessary. For example, this could be a team name or a descriptive string (eg: \"Startup Company\", etc.)."
  } ],
  "http://www.w3.org/2002/07/owl#annotatedProperty" : [ {
    "@id" : "http://www.w3.org/2000/01/rdf-schema#subClassOf"
  } ],
  "http://www.w3.org/2002/07/owl#annotatedSource" : [ {
    "@id" : "http://precis.rukmal.me/ontology#Organization"
  } ],
  "http://www.w3.org/2002/07/owl#annotatedTarget" : [ {
    "@id" : "_:genid165"
  } ]
}, {
  "@id" : "_:genid167",
  "@type" : [ "http://www.w3.org/2002/07/owl#Restriction" ],
  "http://www.w3.org/2002/07/owl#onProperty" : [ {
    "@id" : "http://precis.rukmal.me/ontology#externalResource"
  } ],
  "http://www.w3.org/2002/07/owl#someValuesFrom" : [ {
    "@id" : "http://www.w3.org/2001/XMLSchema#anyURI"
  } ]
}, {
  "@id" : "_:genid168",
  "@type" : [ "http://www.w3.org/2002/07/owl#Restriction" ],
  "http://www.w3.org/2002/07/owl#onDataRange" : [ {
    "@id" : "http://www.w3.org/2001/XMLSchema#string"
  } ],
  "http://www.w3.org/2002/07/owl#onProperty" : [ {
    "@id" : "http://precis.rukmal.me/ontology#hasName"
  } ],
  "http://www.w3.org/2002/07/owl#qualifiedCardinality" : [ {
    "@type" : "http://www.w3.org/2001/XMLSchema#nonNegativeInteger",
    "@value" : "1"
  } ]
}, {
  "@id" : "_:genid169",
  "@type" : [ "http://www.w3.org/2002/07/owl#Restriction" ],
  "http://www.w3.org/2002/07/owl#onDataRange" : [ {
    "@id" : "http://www.w3.org/2001/XMLSchema#anyURI"
  } ],
  "http://www.w3.org/2002/07/owl#onProperty" : [ {
    "@id" : "http://precis.rukmal.me/ontology#hasWebsite"
  } ],
  "http://www.w3.org/2002/07/owl#qualifiedCardinality" : [ {
    "@type" : "http://www.w3.org/2001/XMLSchema#nonNegativeInteger",
    "@value" : "1"
  } ]
}, {
  "@id" : "_:genid170",
  "@type" : [ "http://www.w3.org/2002/07/owl#Restriction" ],
  "http://www.w3.org/2002/07/owl#onProperty" : [ {
    "@id" : "http://precis.rukmal.me/ontology#affiliatedWith"
  } ],
  "http://www.w3.org/2002/07/owl#someValuesFrom" : [ {
    "@id" : "_:genid171"
  } ]
}, {
  "@id" : "_:genid171",
  "@type" : [ "http://www.w3.org/2002/07/owl#Class" ],
  "http://www.w3.org/2002/07/owl#unionOf" : [ {
    "@list" : [ {
      "@id" : "http://precis.rukmal.me/ontology#Degree"
    }, {
      "@id" : "http://precis.rukmal.me/ontology#WorkExperience"
    } ]
  } ]
}, {
  "@id" : "_:genid174",
  "@type" : [ "http://www.w3.org/2002/07/owl#Restriction" ],
  "http://www.w3.org/2002/07/owl#minQualifiedCardinality" : [ {
    "@type" : "http://www.w3.org/2001/XMLSchema#nonNegativeInteger",
    "@value" : "1"
  } ],
  "http://www.w3.org/2002/07/owl#onClass" : [ {
    "@id" : "http://precis.rukmal.me/ontology#Description"
  } ],
  "http://www.w3.org/2002/07/owl#onProperty" : [ {
    "@id" : "http://precis.rukmal.me/ontology#hasDescription"
  } ]
}, {
  "@id" : "_:genid175",
  "@type" : [ "http://www.w3.org/2002/07/owl#Restriction" ],
  "http://www.w3.org/2002/07/owl#onProperty" : [ {
    "@id" : "http://precis.rukmal.me/ontology#endDate"
  } ],
  "http://www.w3.org/2002/07/owl#someValuesFrom" : [ {
    "@id" : "http://www.w3.org/2001/XMLSchema#dateTime"
  } ]
}, {
  "@id" : "_:genid176",
  "@type" : [ "http://www.w3.org/2002/07/owl#Restriction" ],
  "http://www.w3.org/2002/07/owl#onProperty" : [ {
    "@id" : "http://precis.rukmal.me/ontology#externalResource"
  } ],
  "http://www.w3.org/2002/07/owl#someValuesFrom" : [ {
    "@id" : "http://www.w3.org/2001/XMLSchema#anyURI"
  } ]
}, {
  "@id" : "_:genid177",
  "@type" : [ "http://www.w3.org/2002/07/owl#Restriction" ],
  "http://www.w3.org/2002/07/owl#onProperty" : [ {
    "@id" : "http://precis.rukmal.me/ontology#hasMedia"
  } ],
  "http://www.w3.org/2002/07/owl#someValuesFrom" : [ {
    "@id" : "http://www.w3.org/2001/XMLSchema#anyURI"
  } ]
}, {
  "@id" : "_:genid178",
  "@type" : [ "http://www.w3.org/2002/07/owl#Restriction" ],
  "http://www.w3.org/2002/07/owl#minQualifiedCardinality" : [ {
    "@type" : "http://www.w3.org/2001/XMLSchema#nonNegativeInteger",
    "@value" : "1"
  } ],
  "http://www.w3.org/2002/07/owl#onDataRange" : [ {
    "@id" : "http://www.w3.org/2001/XMLSchema#dateTime"
  } ],
  "http://www.w3.org/2002/07/owl#onProperty" : [ {
    "@id" : "http://precis.rukmal.me/ontology#hasDate"
  } ]
}, {
  "@id" : "_:genid179",
  "@type" : [ "http://www.w3.org/2002/07/owl#Restriction" ],
  "http://www.w3.org/2002/07/owl#minQualifiedCardinality" : [ {
    "@type" : "http://www.w3.org/2001/XMLSchema#nonNegativeInteger",
    "@value" : "1"
  } ],
  "http://www.w3.org/2002/07/owl#onDataRange" : [ {
    "@id" : "http://www.w3.org/2001/XMLSchema#anyURI"
  } ],
  "http://www.w3.org/2002/07/owl#onProperty" : [ {
    "@id" : "http://precis.rukmal.me/ontology#hasWebsite"
  } ]
}, {
  "@id" : "_:genid180",
  "@type" : [ "http://www.w3.org/2002/07/owl#Restriction" ],
  "http://www.w3.org/2002/07/owl#onDataRange" : [ {
    "@id" : "http://www.w3.org/2001/XMLSchema#string"
  } ],
  "http://www.w3.org/2002/07/owl#onProperty" : [ {
    "@id" : "http://precis.rukmal.me/ontology#hasName"
  } ],
  "http://www.w3.org/2002/07/owl#qualifiedCardinality" : [ {
    "@type" : "http://www.w3.org/2001/XMLSchema#nonNegativeInteger",
    "@value" : "1"
  } ]
}, {
  "@id" : "_:genid181",
  "@type" : [ "http://www.w3.org/2002/07/owl#Restriction" ],
  "http://www.w3.org/2002/07/owl#onProperty" : [ {
    "@id" : "http://precis.rukmal.me/ontology#hasCollaborators"
  } ],
  "http://www.w3.org/2002/07/owl#someValuesFrom" : [ {
    "@id" : "http://www.w3.org/2001/XMLSchema#string"
  } ]
}, {
  "@id" : "_:genid182",
  "@type" : [ "http://www.w3.org/2002/07/owl#Restriction" ],
  "http://www.w3.org/2002/07/owl#allValuesFrom" : [ {
    "@id" : "http://www.w3.org/2001/XMLSchema#string"
  } ],
  "http://www.w3.org/2002/07/owl#onProperty" : [ {
    "@id" : "http://precis.rukmal.me/ontology#hasAuthors"
  } ]
}, {
  "@id" : "_:genid183",
  "@type" : [ "http://www.w3.org/2002/07/owl#Restriction" ],
  "http://www.w3.org/2002/07/owl#onDataRange" : [ {
    "@id" : "http://www.w3.org/2001/XMLSchema#string"
  } ],
  "http://www.w3.org/2002/07/owl#onProperty" : [ {
    "@id" : "http://precis.rukmal.me/ontology#inConferenceOrJournal"
  } ],
  "http://www.w3.org/2002/07/owl#qualifiedCardinality" : [ {
    "@type" : "http://www.w3.org/2001/XMLSchema#nonNegativeInteger",
    "@value" : "1"
  } ]
}, {
  "@id" : "_:genid184",
  "@type" : [ "http://www.w3.org/2002/07/owl#Restriction" ],
  "http://www.w3.org/2002/07/owl#onDataRange" : [ {
    "@id" : "http://www.w3.org/2001/XMLSchema#string"
  } ],
  "http://www.w3.org/2002/07/owl#onProperty" : [ {
    "@id" : "http://precis.rukmal.me/ontology#inPublication"
  } ],
  "http://www.w3.org/2002/07/owl#qualifiedCardinality" : [ {
    "@type" : "http://www.w3.org/2001/XMLSchema#nonNegativeInteger",
    "@value" : "1"
  } ]
}, {
  "@id" : "_:genid185",
  "@type" : [ "http://www.w3.org/2002/07/owl#Restriction" ],
  "http://www.w3.org/2002/07/owl#maxQualifiedCardinality" : [ {
    "@type" : "http://www.w3.org/2001/XMLSchema#nonNegativeInteger",
    "@value" : "1"
  } ],
  "http://www.w3.org/2002/07/owl#onDataRange" : [ {
    "@id" : "http://www.w3.org/2001/XMLSchema#anyURI"
  } ],
  "http://www.w3.org/2002/07/owl#onProperty" : [ {
    "@id" : "http://precis.rukmal.me/ontology#hasDOI"
  } ]
}, {
  "@id" : "_:genid186",
  "@type" : [ "http://www.w3.org/2002/07/owl#Restriction" ],
  "http://www.w3.org/2002/07/owl#maxQualifiedCardinality" : [ {
    "@type" : "http://www.w3.org/2001/XMLSchema#nonNegativeInteger",
    "@value" : "1"
  } ],
  "http://www.w3.org/2002/07/owl#onDataRange" : [ {
    "@id" : "http://www.w3.org/2001/XMLSchema#string"
  } ],
  "http://www.w3.org/2002/07/owl#onProperty" : [ {
    "@id" : "http://precis.rukmal.me/ontology#hasStatus"
  } ]
}, {
  "@id" : "_:genid187",
  "@type" : [ "http://www.w3.org/2002/07/owl#Restriction" ],
  "http://www.w3.org/2002/07/owl#minQualifiedCardinality" : [ {
    "@type" : "http://www.w3.org/2001/XMLSchema#nonNegativeInteger",
    "@value" : "1"
  } ],
  "http://www.w3.org/2002/07/owl#onClass" : [ {
    "@id" : "http://precis.rukmal.me/ontology#SkillGroup"
  } ],
  "http://www.w3.org/2002/07/owl#onProperty" : [ {
    "@id" : "http://precis.rukmal.me/ontology#inSkillGroup"
  } ]
}, {
  "@id" : "_:genid188",
  "@type" : [ "http://www.w3.org/2002/07/owl#Restriction" ],
  "http://www.w3.org/2002/07/owl#onProperty" : [ {
    "@id" : "http://precis.rukmal.me/ontology#externalResource"
  } ],
  "http://www.w3.org/2002/07/owl#someValuesFrom" : [ {
    "@id" : "http://www.w3.org/2001/XMLSchema#anyURI"
  } ]
}, {
  "@id" : "_:genid189",
  "@type" : [ "http://www.w3.org/2002/07/owl#Restriction" ],
  "http://www.w3.org/2002/07/owl#onDataRange" : [ {
    "@id" : "http://www.w3.org/2001/XMLSchema#string"
  } ],
  "http://www.w3.org/2002/07/owl#onProperty" : [ {
    "@id" : "http://precis.rukmal.me/ontology#hasName"
  } ],
  "http://www.w3.org/2002/07/owl#qualifiedCardinality" : [ {
    "@type" : "http://www.w3.org/2001/XMLSchema#nonNegativeInteger",
    "@value" : "1"
  } ]
}, {
  "@id" : "_:genid19",
  "@type" : [ "http://www.w3.org/2002/07/owl#Class" ],
  "http://www.w3.org/2002/07/owl#unionOf" : [ {
    "@list" : [ {
      "@id" : "http://precis.rukmal.me/ontology#Accolade"
    }, {
      "@id" : "http://precis.rukmal.me/ontology#Portfolio"
    } ]
  } ]
}, {
  "@id" : "_:genid190",
  "@type" : [ "http://www.w3.org/2002/07/owl#Restriction" ],
  "http://www.w3.org/2002/07/owl#onProperty" : [ {
    "@id" : "http://precis.rukmal.me/ontology#hasDescription"
  } ],
  "http://www.w3.org/2002/07/owl#someValuesFrom" : [ {
    "@id" : "http://precis.rukmal.me/ontology#Description"
  } ]
}, {
  "@id" : "_:genid191",
  "@type" : [ "http://www.w3.org/2002/07/owl#Restriction" ],
  "http://www.w3.org/2002/07/owl#minQualifiedCardinality" : [ {
    "@type" : "http://www.w3.org/2001/XMLSchema#nonNegativeInteger",
    "@value" : "1"
  } ],
  "http://www.w3.org/2002/07/owl#onClass" : [ {
    "@id" : "http://precis.rukmal.me/ontology#Skill"
  } ],
  "http://www.w3.org/2002/07/owl#onProperty" : [ {
    "@id" : "http://precis.rukmal.me/ontology#hasSkill"
  } ]
}, {
  "@id" : "_:genid192",
  "@type" : [ "http://www.w3.org/2002/07/owl#Restriction" ],
  "http://www.w3.org/2002/07/owl#onProperty" : [ {
    "@id" : "http://precis.rukmal.me/ontology#externalResource"
  } ],
  "http://www.w3.org/2002/07/owl#someValuesFrom" : [ {
    "@id" : "http://www.w3.org/2001/XMLSchema#anyURI"
  } ]
}, {
  "@id" : "_:genid193",
  "@type" : [ "http://www.w3.org/2002/07/owl#Restriction" ],
  "http://www.w3.org/2002/07/owl#onDataRange" : [ {
    "@id" : "http://www.w3.org/2001/XMLSchema#string"
  } ],
  "http://www.w3.org/2002/07/owl#onProperty" : [ {
    "@id" : "http://precis.rukmal.me/ontology#hasName"
  } ],
  "http://www.w3.org/2002/07/owl#qualifiedCardinality" : [ {
    "@type" : "http://www.w3.org/2001/XMLSchema#nonNegativeInteger",
    "@value" : "1"
  } ]
}, {
  "@id" : "_:genid194",
  "@type" : [ "http://www.w3.org/2002/07/owl#Restriction" ],
  "http://www.w3.org/2002/07/owl#minQualifiedCardinality" : [ {
    "@type" : "http://www.w3.org/2001/XMLSchema#nonNegativeInteger",
    "@value" : "1"
  } ],
  "http://www.w3.org/2002/07/owl#onClass" : [ {
    "@id" : "http://precis.rukmal.me/ontology#KnowledgeArea"
  } ],
  "http://www.w3.org/2002/07/owl#onProperty" : [ {
    "@id" : "http://precis.rukmal.me/ontology#inKnowledgeArea"
  } ]
}, {
  "@id" : "_:genid195",
  "@type" : [ "http://www.w3.org/2002/07/owl#Restriction" ],
  "http://www.w3.org/2002/07/owl#minQualifiedCardinality" : [ {
    "@type" : "http://www.w3.org/2001/XMLSchema#nonNegativeInteger",
    "@value" : "1"
  } ],
  "http://www.w3.org/2002/07/owl#onDataRange" : [ {
    "@id" : "http://www.w3.org/2001/XMLSchema#string"
  } ],
  "http://www.w3.org/2002/07/owl#onProperty" : [ {
    "@id" : "http://precis.rukmal.me/ontology#hasName"
  } ]
}, {
  "@id" : "_:genid196",
  "@type" : [ "http://www.w3.org/2002/07/owl#Restriction" ],
  "http://www.w3.org/2002/07/owl#onProperty" : [ {
    "@id" : "http://precis.rukmal.me/ontology#hasCollaborators"
  } ],
  "http://www.w3.org/2002/07/owl#someValuesFrom" : [ {
    "@id" : "http://www.w3.org/2001/XMLSchema#string"
  } ]
}, {
  "@id" : "_:genid197",
  "@type" : [ "http://www.w3.org/2002/07/owl#Restriction" ],
  "http://www.w3.org/2002/07/owl#minQualifiedCardinality" : [ {
    "@type" : "http://www.w3.org/2001/XMLSchema#nonNegativeInteger",
    "@value" : "1"
  } ],
  "http://www.w3.org/2002/07/owl#onDataRange" : [ {
    "@id" : "http://www.w3.org/2001/XMLSchema#dateTime"
  } ],
  "http://www.w3.org/2002/07/owl#onProperty" : [ {
    "@id" : "http://precis.rukmal.me/ontology#hasDate"
  } ]
}, {
  "@id" : "_:genid198",
  "@type" : [ "http://www.w3.org/2002/07/owl#Class" ],
  "http://www.w3.org/2002/07/owl#unionOf" : [ {
    "@list" : [ {
      "@id" : "_:genid202"
    }, {
      "@id" : "_:genid200"
    } ]
  } ]
}, {
  "@id" : "_:genid200",
  "@type" : [ "http://www.w3.org/2002/07/owl#Restriction" ],
  "http://www.w3.org/2002/07/owl#onDataRange" : [ {
    "@id" : "http://www.w3.org/2001/XMLSchema#string"
  } ],
  "http://www.w3.org/2002/07/owl#onProperty" : [ {
    "@id" : "http://precis.rukmal.me/ontology#inState"
  } ],
  "http://www.w3.org/2002/07/owl#qualifiedCardinality" : [ {
    "@type" : "http://www.w3.org/2001/XMLSchema#nonNegativeInteger",
    "@value" : "1"
  } ]
}, {
  "@id" : "_:genid202",
  "@type" : [ "http://www.w3.org/2002/07/owl#Restriction" ],
  "http://www.w3.org/2002/07/owl#onDataRange" : [ {
    "@id" : "http://www.w3.org/2001/XMLSchema#string"
  } ],
  "http://www.w3.org/2002/07/owl#onProperty" : [ {
    "@id" : "http://precis.rukmal.me/ontology#inCountry"
  } ],
  "http://www.w3.org/2002/07/owl#qualifiedCardinality" : [ {
    "@type" : "http://www.w3.org/2001/XMLSchema#nonNegativeInteger",
    "@value" : "1"
  } ]
}, {
  "@id" : "_:genid203",
  "@type" : [ "http://www.w3.org/2002/07/owl#Restriction" ],
  "http://www.w3.org/2002/07/owl#minQualifiedCardinality" : [ {
    "@type" : "http://www.w3.org/2001/XMLSchema#nonNegativeInteger",
    "@value" : "1"
  } ],
  "http://www.w3.org/2002/07/owl#onClass" : [ {
    "@id" : "http://precis.rukmal.me/ontology#Description"
  } ],
  "http://www.w3.org/2002/07/owl#onProperty" : [ {
    "@id" : "http://precis.rukmal.me/ontology#hasDescription"
  } ]
}, {
  "@id" : "_:genid204",
  "@type" : [ "http://www.w3.org/2002/07/owl#Restriction" ],
  "http://www.w3.org/2002/07/owl#onClass" : [ {
    "@id" : "http://precis.rukmal.me/ontology#Organization"
  } ],
  "http://www.w3.org/2002/07/owl#onProperty" : [ {
    "@id" : "http://precis.rukmal.me/ontology#employedAt"
  } ],
  "http://www.w3.org/2002/07/owl#qualifiedCardinality" : [ {
    "@type" : "http://www.w3.org/2001/XMLSchema#nonNegativeInteger",
    "@value" : "1"
  } ]
}, {
  "@id" : "_:genid205",
  "@type" : [ "http://www.w3.org/2002/07/owl#Restriction" ],
  "http://www.w3.org/2002/07/owl#onProperty" : [ {
    "@id" : "http://precis.rukmal.me/ontology#endDate"
  } ],
  "http://www.w3.org/2002/07/owl#someValuesFrom" : [ {
    "@id" : "http://www.w3.org/2001/XMLSchema#dateTime"
  } ]
}, {
  "@id" : "_:genid206",
  "@type" : [ "http://www.w3.org/2002/07/owl#Restriction" ],
  "http://www.w3.org/2002/07/owl#onProperty" : [ {
    "@id" : "http://precis.rukmal.me/ontology#hasImage"
  } ],
  "http://www.w3.org/2002/07/owl#someValuesFrom" : [ {
    "@id" : "http://www.w3.org/2001/XMLSchema#anyURI"
  } ]
}, {
  "@id" : "_:genid207",
  "@type" : [ "http://www.w3.org/2002/07/owl#Restriction" ],
  "http://www.w3.org/2002/07/owl#onProperty" : [ {
    "@id" : "http://precis.rukmal.me/ontology#hasMedia"
  } ],
  "http://www.w3.org/2002/07/owl#someValuesFrom" : [ {
    "@id" : "http://www.w3.org/2001/XMLSchema#anyURI"
  } ]
}, {
  "@id" : "_:genid208",
  "@type" : [ "http://www.w3.org/2002/07/owl#Restriction" ],
  "http://www.w3.org/2002/07/owl#onDataRange" : [ {
    "@id" : "http://www.w3.org/2001/XMLSchema#dateTime"
  } ],
  "http://www.w3.org/2002/07/owl#onProperty" : [ {
    "@id" : "http://precis.rukmal.me/ontology#hasDate"
  } ],
  "http://www.w3.org/2002/07/owl#qualifiedCardinality" : [ {
    "@type" : "http://www.w3.org/2001/XMLSchema#nonNegativeInteger",
    "@value" : "1"
  } ]
}, {
  "@id" : "_:genid209",
  "@type" : [ "http://www.w3.org/2002/07/owl#Restriction" ],
  "http://www.w3.org/2002/07/owl#onDataRange" : [ {
    "@id" : "http://www.w3.org/2001/XMLSchema#string"
  } ],
  "http://www.w3.org/2002/07/owl#onProperty" : [ {
    "@id" : "http://precis.rukmal.me/ontology#hasName"
  } ],
  "http://www.w3.org/2002/07/owl#qualifiedCardinality" : [ {
    "@type" : "http://www.w3.org/2001/XMLSchema#nonNegativeInteger",
    "@value" : "1"
  } ]
}, {
  "@id" : "_:genid210",
  "@type" : [ "http://www.w3.org/2002/07/owl#Restriction" ],
  "http://www.w3.org/2002/07/owl#onDataRange" : [ {
    "@id" : "http://www.w3.org/2001/XMLSchema#string"
  } ],
  "http://www.w3.org/2002/07/owl#onProperty" : [ {
    "@id" : "http://precis.rukmal.me/ontology#inCity"
  } ],
  "http://www.w3.org/2002/07/owl#qualifiedCardinality" : [ {
    "@type" : "http://www.w3.org/2001/XMLSchema#nonNegativeInteger",
    "@value" : "1"
  } ]
}, {
  "@id" : "_:genid211",
  "@type" : [ "http://www.w3.org/2002/07/owl#AllDisjointClasses" ],
  "http://www.w3.org/2002/07/owl#members" : [ {
    "@list" : [ {
      "@id" : "http://precis.rukmal.me/ontology#Accolade"
    }, {
      "@id" : "http://precis.rukmal.me/ontology#ActivityType"
    }, {
      "@id" : "http://precis.rukmal.me/ontology#Course"
    }, {
      "@id" : "http://precis.rukmal.me/ontology#Degree"
    }, {
      "@id" : "http://precis.rukmal.me/ontology#Description"
    }, {
      "@id" : "http://precis.rukmal.me/ontology#KnowledgeArea"
    }, {
      "@id" : "http://precis.rukmal.me/ontology#Organization"
    }, {
      "@id" : "http://precis.rukmal.me/ontology#Portfolio"
    }, {
      "@id" : "http://precis.rukmal.me/ontology#SkillGroup"
    }, {
      "@id" : "http://precis.rukmal.me/ontology#WorkExperience"
    } ]
  } ]
}, {
  "@id" : "_:genid22",
  "@type" : [ "http://www.w3.org/2002/07/owl#Class" ],
  "http://www.w3.org/2002/07/owl#unionOf" : [ {
    "@list" : [ {
      "@id" : "http://precis.rukmal.me/ontology#Accolade"
    }, {
      "@id" : "http://precis.rukmal.me/ontology#Activity"
    }, {
      "@id" : "http://precis.rukmal.me/ontology#Course"
    }, {
      "@id" : "http://precis.rukmal.me/ontology#Degree"
    }, {
      "@id" : "http://precis.rukmal.me/ontology#Portfolio"
    }, {
      "@id" : "http://precis.rukmal.me/ontology#Skill"
    }, {
      "@id" : "http://precis.rukmal.me/ontology#Subject"
    }, {
      "@id" : "http://precis.rukmal.me/ontology#WorkExperience"
    } ]
  } ]
}, {
  "@id" : "_:genid31",
  "@type" : [ "http://www.w3.org/2002/07/owl#Class" ],
  "http://www.w3.org/2002/07/owl#unionOf" : [ {
    "@list" : [ {
      "@id" : "http://precis.rukmal.me/ontology#Accolade"
    }, {
      "@id" : "http://precis.rukmal.me/ontology#Activity"
    }, {
      "@id" : "http://precis.rukmal.me/ontology#Course"
    }, {
      "@id" : "http://precis.rukmal.me/ontology#Degree"
    }, {
      "@id" : "http://precis.rukmal.me/ontology#Portfolio"
    }, {
      "@id" : "http://precis.rukmal.me/ontology#Skill"
    }, {
      "@id" : "http://precis.rukmal.me/ontology#Subject"
    }, {
      "@id" : "http://precis.rukmal.me/ontology#WorkExperience"
    } ]
  } ]
}, {
  "@id" : "_:genid4",
  "@type" : [ "http://www.w3.org/2002/07/owl#Class" ],
  "http://www.w3.org/2002/07/owl#unionOf" : [ {
    "@list" : [ {
      "@id" : "http://precis.rukmal.me/ontology#Degree"
    }, {
      "@id" : "http://precis.rukmal.me/ontology#WorkExperience"
    } ]
  } ]
}, {
  "@id" : "_:genid40",
  "@type" : [ "http://www.w3.org/2000/01/rdf-schema#Datatype" ],
  "http://www.w3.org/2002/07/owl#onDatatype" : [ {
    "@id" : "http://www.w3.org/2001/XMLSchema#double"
  } ],
  "http://www.w3.org/2002/07/owl#withRestrictions" : [ {
    "@list" : [ {
      "@id" : "_:genid44"
    }, {
      "@id" : "_:genid42"
    } ]
  } ]
}, {
  "@id" : "_:genid42",
  "http://www.w3.org/2001/XMLSchema#maxInclusive" : [ {
    "@type" : "http://www.w3.org/2001/XMLSchema#double",
    "@value" : "4.0"
  } ]
}, {
  "@id" : "_:genid44",
  "http://www.w3.org/2001/XMLSchema#minInclusive" : [ {
    "@type" : "http://www.w3.org/2001/XMLSchema#double",
    "@value" : "0.0"
  } ]
}, {
  "@id" : "_:genid45",
  "@type" : [ "http://www.w3.org/2002/07/owl#Class" ],
  "http://www.w3.org/2002/07/owl#unionOf" : [ {
    "@list" : [ {
      "@id" : "http://precis.rukmal.me/ontology#ActivityType"
    }, {
      "@id" : "http://precis.rukmal.me/ontology#Course"
    }, {
      "@id" : "http://precis.rukmal.me/ontology#Portfolio"
    }, {
      "@id" : "http://precis.rukmal.me/ontology#WorkExperience"
    } ]
  } ]
}, {
  "@id" : "_:genid50",
  "@type" : [ "http://www.w3.org/2002/07/owl#Class" ],
  "http://www.w3.org/2002/07/owl#unionOf" : [ {
    "@list" : [ {
      "@id" : "http://precis.rukmal.me/ontology#Accolade"
    }, {
      "@id" : "http://precis.rukmal.me/ontology#ActivityType"
    }, {
      "@id" : "http://precis.rukmal.me/ontology#Course"
    }, {
      "@id" : "http://precis.rukmal.me/ontology#Degree"
    }, {
      "@id" : "http://precis.rukmal.me/ontology#KnowledgeArea"
    }, {
      "@id" : "http://precis.rukmal.me/ontology#Organization"
    }, {
      "@id" : "http://precis.rukmal.me/ontology#Portfolio"
    }, {
      "@id" : "http://precis.rukmal.me/ontology#SkillGroup"
    }, {
      "@id" : "http://precis.rukmal.me/ontology#WorkExperience"
    } ]
  } ]
}, {
  "@id" : "_:genid60",
  "@type" : [ "http://www.w3.org/2002/07/owl#Class" ],
  "http://www.w3.org/2002/07/owl#unionOf" : [ {
    "@list" : [ {
      "@id" : "http://precis.rukmal.me/ontology#Accolade"
    }, {
      "@id" : "http://precis.rukmal.me/ontology#ActivityType"
    }, {
      "@id" : "http://precis.rukmal.me/ontology#Course"
    }, {
      "@id" : "http://precis.rukmal.me/ontology#Degree"
    }, {
      "@id" : "http://precis.rukmal.me/ontology#Portfolio"
    }, {
      "@id" : "http://precis.rukmal.me/ontology#WorkExperience"
    } ]
  } ]
}, {
  "@id" : "_:genid67",
  "@type" : [ "http://www.w3.org/2002/07/owl#Class" ],
  "http://www.w3.org/2002/07/owl#unionOf" : [ {
    "@list" : [ {
      "@id" : "http://precis.rukmal.me/ontology#Accolade"
    }, {
      "@id" : "http://precis.rukmal.me/ontology#ActivityType"
    }, {
      "@id" : "http://precis.rukmal.me/ontology#Portfolio"
    }, {
      "@id" : "http://precis.rukmal.me/ontology#WorkExperience"
    } ]
  } ]
}, {
  "@id" : "_:genid7",
  "@type" : [ "http://www.w3.org/2002/07/owl#Class" ],
  "http://www.w3.org/2002/07/owl#unionOf" : [ {
    "@list" : [ {
      "@id" : "http://precis.rukmal.me/ontology#Accolade"
    }, {
      "@id" : "http://precis.rukmal.me/ontology#ActivityType"
    }, {
      "@id" : "http://precis.rukmal.me/ontology#Course"
    }, {
      "@id" : "http://precis.rukmal.me/ontology#KnowledgeArea"
    }, {
      "@id" : "http://precis.rukmal.me/ontology#Organization"
    }, {
      "@id" : "http://precis.rukmal.me/ontology#Portfolio"
    }, {
      "@id" : "http://precis.rukmal.me/ontology#SkillGroup"
    }, {
      "@id" : "http://precis.rukmal.me/ontology#WorkExperience"
    } ]
  } ]
}, {
  "@id" : "_:genid72",
  "@type" : [ "http://www.w3.org/2002/07/owl#Class" ],
  "http://www.w3.org/2002/07/owl#unionOf" : [ {
    "@list" : [ {
      "@id" : "http://precis.rukmal.me/ontology#Accolade"
    }, {
      "@id" : "http://precis.rukmal.me/ontology#ActivityType"
    }, {
      "@id" : "http://precis.rukmal.me/ontology#Course"
    }, {
      "@id" : "http://precis.rukmal.me/ontology#Degree"
    }, {
      "@id" : "http://precis.rukmal.me/ontology#KnowledgeArea"
    }, {
      "@id" : "http://precis.rukmal.me/ontology#Organization"
    }, {
      "@id" : "http://precis.rukmal.me/ontology#Portfolio"
    }, {
      "@id" : "http://precis.rukmal.me/ontology#SkillGroup"
    }, {
      "@id" : "http://precis.rukmal.me/ontology#WorkExperience"
    } ]
  } ]
}, {
  "@id" : "_:genid82",
  "@type" : [ "http://www.w3.org/2002/07/owl#Class" ],
  "http://www.w3.org/2002/07/owl#unionOf" : [ {
    "@list" : [ {
      "@id" : "http://precis.rukmal.me/ontology#Accolade"
    }, {
      "@id" : "http://precis.rukmal.me/ontology#ActivityType"
    }, {
      "@id" : "http://precis.rukmal.me/ontology#Course"
    }, {
      "@id" : "http://precis.rukmal.me/ontology#Degree"
    }, {
      "@id" : "http://precis.rukmal.me/ontology#Organization"
    }, {
      "@id" : "http://precis.rukmal.me/ontology#Portfolio"
    }, {
      "@id" : "http://precis.rukmal.me/ontology#SkillGroup"
    }, {
      "@id" : "http://precis.rukmal.me/ontology#WorkExperience"
    } ]
  } ]
}, {
  "@id" : "_:genid91",
  "@type" : [ "http://www.w3.org/2002/07/owl#Class" ],
  "http://www.w3.org/2002/07/owl#unionOf" : [ {
    "@list" : [ {
      "@id" : "http://precis.rukmal.me/ontology#Accolade"
    }, {
      "@id" : "http://precis.rukmal.me/ontology#ActivityType"
    }, {
      "@id" : "http://precis.rukmal.me/ontology#Course"
    }, {
      "@id" : "http://precis.rukmal.me/ontology#Degree"
    }, {
      "@id" : "http://precis.rukmal.me/ontology#Organization"
    }, {
      "@id" : "http://precis.rukmal.me/ontology#Portfolio"
    }, {
      "@id" : "http://precis.rukmal.me/ontology#SkillGroup"
    }, {
      "@id" : "http://precis.rukmal.me/ontology#WorkExperience"
    } ]
  } ]
}, {
  "@id" : "http://precis.rukmal.me/ontology",
  "@type" : [ "http://www.w3.org/2002/07/owl#Ontology" ],
  "http://purl.org/dc/elements/1.1/abstract" : [ {
    "@value" : "The Precis ontology is designed to encapsulate portfolio information about an individual. This includes information that would traditionally be presented in a Resume/CV. This ontology is designed to be used with the Precis toolkit; see http://precis.rukmal.me for more.\n\nCurrently, this ontology powers a templating engine to generate dyanmic resumes, but has the potential to power other personal data driven experiences."
  } ],
  "http://purl.org/dc/elements/1.1/creator" : [ {
    "@value" : "Rukmal Weerawarana"
  } ],
  "http://purl.org/dc/elements/1.1/title" : [ {
    "@value" : "Precis Ontology"
  } ],
  "http://purl.org/dc/terms/created" : [ {
    "@type" : "http://www.w3.org/2001/XMLSchema#dateTime",
    "@value" : "2019-04-07T00:00:00"
  } ],
  "http://purl.org/dc/terms/creator" : [ {
    "@id" : "http://rukmal.me"
  } ],
  "http://purl.org/dc/terms/modified" : [ {
    "@type" : "http://www.w3.org/2001/XMLSchema#dateTime",
    "@value" : "2019-04-17T00:00:00"
  } ],
  "http://purl.org/ontology/bibo/doi" : [ {
    "@id" : "http://purl.org/precis"
  } ],
  "http://purl.org/vocab/vann/preferredNamespacePrefix" : [ {
    "@value" : "precis"
  } ],
  "http://purl.org/vocab/vann/preferredNamespaceUri" : [ {
    "@value" : "http://precis.rukmal.me/ontology"
  } ],
  "http://schema.org/license" : [ {
    "@id" : "https://github.com/rukmal/precis/blob/master/LICENSE"
  } ],
  "http://www.w3.org/2000/01/rdf-schema#comment" : [ {
    "@value" : "The Precis ontology is designed to encapsulate portfolio information about an individual. This includes information that would traditionally be presented in a Resume/CV. This ontology is designed to be used with the Precis toolkit; see http://precis.rukmal.me for more.\n\nCurrently, this ontology powers a templating engine to generate dyanmic resumes, but has the potential to power other personal data driven experiences."
  } ],
  "http://www.w3.org/2002/07/owl#priorVersion" : [ {
    "@id" : "https://github.com/rukmal/precis/releases/download/1.4.0/precis_ontology.rdf"
  } ],
  "http://www.w3.org/2002/07/owl#versionIRI" : [ {
    "@id" : "http://precis.rukmal.me/ontology/1.5.0"
  } ],
  "http://www.w3.org/2002/07/owl#versionInfo" : [ {
    "@value" : "1.5.0"
  } ]
}, {
  "@id" : "http://precis.rukmal.me/ontology#Accolade",
  "@type" : [ "http://www.w3.org/2002/07/owl#Class" ],
  "http://www.w3.org/2000/01/rdf-schema#comment" : [ {
    "@value" : "An accolade. This is either an 'Award' or a 'Certification'."
  } ],
  "http://www.w3.org/2000/01/rdf-schema#label" : [ {
    "@value" : "Accolade"
  } ],
  "http://www.w3.org/2000/01/rdf-schema#subClassOf" : [ {
    "@id" : "_:genid122"
  }, {
    "@id" : "_:genid126"
  }, {
    "@id" : "_:genid127"
  }, {
    "@id" : "_:genid128"
  }, {
    "@id" : "_:genid129"
  }, {
    "@id" : "_:genid130"
  } ]
}, {
  "@id" : "http://precis.rukmal.me/ontology#Activity",
  "@type" : [ "http://www.w3.org/2002/07/owl#Class" ],
  "http://www.w3.org/2000/01/rdf-schema#comment" : [ {
    "@value" : "A specific activity, such as a specific hackathon or volunteering experience."
  } ],
  "http://www.w3.org/2000/01/rdf-schema#label" : [ {
    "@value" : "Activity"
  } ],
  "http://www.w3.org/2000/01/rdf-schema#subClassOf" : [ {
    "@id" : "http://precis.rukmal.me/ontology#ActivityType"
  }, {
    "@id" : "_:genid131"
  } ]
}, {
  "@id" : "http://precis.rukmal.me/ontology#ActivityType",
  "@type" : [ "http://www.w3.org/2002/07/owl#Class" ],
  "http://www.w3.org/2000/01/rdf-schema#comment" : [ {
    "@value" : "Type of the activity (typically a larger supergroup), such as \"Hackathon\" or \"Volunteering\"."
  } ],
  "http://www.w3.org/2000/01/rdf-schema#label" : [ {
    "@value" : "Activity Type"
  } ],
  "http://www.w3.org/2000/01/rdf-schema#subClassOf" : [ {
    "@id" : "_:genid132"
  }, {
    "@id" : "_:genid133"
  }, {
    "@id" : "_:genid134"
  }, {
    "@id" : "_:genid135"
  }, {
    "@id" : "_:genid136"
  }, {
    "@id" : "_:genid137"
  }, {
    "@id" : "_:genid138"
  } ]
}, {
  "@id" : "http://precis.rukmal.me/ontology#Award",
  "@type" : [ "http://www.w3.org/2002/07/owl#Class" ],
  "http://www.w3.org/2000/01/rdf-schema#comment" : [ {
    "@value" : "An 'Award'; this would correspond to a traditional award, such as a Fellowship or Dean's List."
  } ],
  "http://www.w3.org/2000/01/rdf-schema#label" : [ {
    "@value" : "Award"
  } ],
  "http://www.w3.org/2000/01/rdf-schema#subClassOf" : [ {
    "@id" : "http://precis.rukmal.me/ontology#Accolade"
  } ]
}, {
  "@id" : "http://precis.rukmal.me/ontology#Certification",
  "@type" : [ "http://www.w3.org/2002/07/owl#Class" ],
  "http://www.w3.org/2000/01/rdf-schema#comment" : [ {
    "@value" : "A 'Cerficiation'; this would correspond to a traditional certification, such as a CPR Rating, or the Bloomberg Market Concepts certification."
  } ],
  "http://www.w3.org/2000/01/rdf-schema#label" : [ {
    "@value" : "Certification"
  } ],
  "http://www.w3.org/2000/01/rdf-schema#subClassOf" : [ {
    "@id" : "http://precis.rukmal.me/ontology#Accolade"
  } ]
}, {
  "@id" : "http://precis.rukmal.me/ontology#Course",
  "@type" : [ "http://www.w3.org/2002/07/owl#Class" ],
  "http://www.w3.org/2000/01/rdf-schema#comment" : [ {
    "@value" : "A course. This would typically be an item that is included in the \"Relevant Coursework\" section of a Resume/CV."
  } ],
  "http://www.w3.org/2000/01/rdf-schema#label" : [ {
    "@value" : "Course"
  } ],
  "http://www.w3.org/2000/01/rdf-schema#subClassOf" : [ {
    "@id" : "_:genid139"
  }, {
    "@id" : "_:genid140"
  }, {
    "@id" : "_:genid141"
  }, {
    "@id" : "_:genid142"
  }, {
    "@id" : "_:genid143"
  }, {
    "@id" : "_:genid144"
  }, {
    "@id" : "_:genid145"
  }, {
    "@id" : "_:genid146"
  }, {
    "@id" : "_:genid147"
  } ]
}, {
  "@id" : "http://precis.rukmal.me/ontology#Degree",
  "@type" : [ "http://www.w3.org/2002/07/owl#Class" ],
  "http://www.w3.org/2000/01/rdf-schema#comment" : [ {
    "@value" : "A Degree, which was completed at a specific institution, in a specific school and department. Optional media links to pictures can be included for rendering at the time of presentation. Records the year and month that the degree was (or is expected to be) awarded."
  } ],
  "http://www.w3.org/2000/01/rdf-schema#label" : [ {
    "@value" : "Degree"
  } ],
  "http://www.w3.org/2000/01/rdf-schema#subClassOf" : [ {
    "@id" : "_:genid148"
  }, {
    "@id" : "_:genid149"
  }, {
    "@id" : "_:genid150"
  }, {
    "@id" : "_:genid151"
  }, {
    "@id" : "_:genid152"
  }, {
    "@id" : "_:genid153"
  }, {
    "@id" : "_:genid154"
  }, {
    "@id" : "_:genid155"
  }, {
    "@id" : "_:genid156"
  }, {
    "@id" : "_:genid157"
  } ]
}, {
  "@id" : "http://precis.rukmal.me/ontology#Description",
  "@type" : [ "http://www.w3.org/2002/07/owl#Class" ],
  "http://www.w3.org/2000/01/rdf-schema#comment" : [ {
    "@value" : "This description is associated with any other concept, providing a description. It has the capability to track priority levels, which can be used to intelligently truncate a series of descriptions when creating a Resume/CV with the command line toolkit."
  } ],
  "http://www.w3.org/2000/01/rdf-schema#label" : [ {
    "@value" : "Description for a given item"
  } ],
  "http://www.w3.org/2000/01/rdf-schema#subClassOf" : [ {
    "@id" : "_:genid158"
  }, {
    "@id" : "_:genid159"
  } ]
}, {
  "@id" : "http://precis.rukmal.me/ontology#KnowledgeArea",
  "@type" : [ "http://www.w3.org/2002/07/owl#Class" ],
  "http://www.w3.org/2000/01/rdf-schema#comment" : [ {
    "@value" : "Knowledge Area parent group. This would be something along the lines of \"Mathematics\", or \"Computer Science\"."
  } ],
  "http://www.w3.org/2000/01/rdf-schema#label" : [ {
    "@value" : "Knowledge Area"
  } ],
  "http://www.w3.org/2000/01/rdf-schema#subClassOf" : [ {
    "@id" : "_:genid160"
  }, {
    "@id" : "_:genid161"
  }, {
    "@id" : "_:genid162"
  }, {
    "@id" : "_:genid163"
  } ]
}, {
  "@id" : "http://precis.rukmal.me/ontology#Organization",
  "@type" : [ "http://www.w3.org/2002/07/owl#Class" ],
  "http://www.w3.org/2000/01/rdf-schema#comment" : [ {
    "@value" : "An organization; this can be a company, university, a specific university department, etc."
  } ],
  "http://www.w3.org/2000/01/rdf-schema#label" : [ {
    "@value" : "Organization"
  } ],
  "http://www.w3.org/2000/01/rdf-schema#subClassOf" : [ {
    "@id" : "_:genid164"
  }, {
    "@id" : "_:genid165"
  }, {
    "@id" : "_:genid167"
  }, {
    "@id" : "_:genid168"
  }, {
    "@id" : "_:genid169"
  } ]
}, {
  "@id" : "http://precis.rukmal.me/ontology#Portfolio",
  "@type" : [ "http://www.w3.org/2002/07/owl#Class" ],
  "http://www.w3.org/2000/01/rdf-schema#comment" : [ {
    "@value" : "A Portfolio item; this can be a Talk, Publication, Project, etc."
  } ],
  "http://www.w3.org/2000/01/rdf-schema#label" : [ {
    "@value" : "Portfolio"
  } ],
  "http://www.w3.org/2000/01/rdf-schema#subClassOf" : [ {
    "@id" : "_:genid170"
  }, {
    "@id" : "_:genid174"
  }, {
    "@id" : "_:genid175"
  }, {
    "@id" : "_:genid176"
  }, {
    "@id" : "_:genid177"
  }, {
    "@id" : "_:genid178"
  }, {
    "@id" : "_:genid179"
  }, {
    "@id" : "_:genid180"
  } ]
}, {
  "@id" : "http://precis.rukmal.me/ontology#Project",
  "@type" : [ "http://www.w3.org/2002/07/owl#Class" ],
  "http://www.w3.org/2000/01/rdf-schema#comment" : [ {
    "@value" : "A project, such as a final year report, or a video produced for a class."
  } ],
  "http://www.w3.org/2000/01/rdf-schema#label" : [ {
    "@value" : "Project"
  } ],
  "http://www.w3.org/2000/01/rdf-schema#subClassOf" : [ {
    "@id" : "http://precis.rukmal.me/ontology#Portfolio"
  }, {
    "@id" : "_:genid181"
  } ]
}, {
  "@id" : "http://precis.rukmal.me/ontology#Publication",
  "@type" : [ "http://www.w3.org/2002/07/owl#Class" ],
  "http://www.w3.org/2000/01/rdf-schema#comment" : [ {
    "@value" : "A publication, typically limited to peer reviewed articles."
  } ],
  "http://www.w3.org/2000/01/rdf-schema#label" : [ {
    "@value" : "Publication"
  } ],
  "http://www.w3.org/2000/01/rdf-schema#subClassOf" : [ {
    "@id" : "http://precis.rukmal.me/ontology#Portfolio"
  }, {
    "@id" : "_:genid182"
  }, {
    "@id" : "_:genid183"
  }, {
    "@id" : "_:genid184"
  }, {
    "@id" : "_:genid185"
  }, {
    "@id" : "_:genid186"
  } ]
}, {
  "@id" : "http://precis.rukmal.me/ontology#Skill",
  "@type" : [ "http://www.w3.org/2002/07/owl#Class" ],
  "http://www.w3.org/2000/01/rdf-schema#comment" : [ {
    "@value" : "An individual skill. Each skill belongs to a specific SkillGroup. For example; \"Python\", \"R\", and \"Java\" would all be skills, in the \"Programming Languages\" SkillGroup."
  } ],
  "http://www.w3.org/2000/01/rdf-schema#label" : [ {
    "@value" : "Skill"
  } ],
  "http://www.w3.org/2000/01/rdf-schema#subClassOf" : [ {
    "@id" : "http://precis.rukmal.me/ontology#SkillGroup"
  }, {
    "@id" : "_:genid187"
  }, {
    "@id" : "_:genid188"
  }, {
    "@id" : "_:genid189"
  } ]
}, {
  "@id" : "http://precis.rukmal.me/ontology#SkillGroup",
  "@type" : [ "http://www.w3.org/2002/07/owl#Class" ],
  "http://www.w3.org/2000/01/rdf-schema#comment" : [ {
    "@value" : "A Skill Group. This group can contain one or more Skills. For example, \"Python\", \"R\", and \"Java\" would all be in the \"Programming Languages\" Skill Group."
  } ],
  "http://www.w3.org/2000/01/rdf-schema#label" : [ {
    "@value" : "Skill Group"
  } ],
  "http://www.w3.org/2000/01/rdf-schema#subClassOf" : [ {
    "@id" : "_:genid190"
  }, {
    "@id" : "_:genid191"
  }, {
    "@id" : "_:genid192"
  }, {
    "@id" : "_:genid193"
  } ]
}, {
  "@id" : "http://precis.rukmal.me/ontology#Subject",
  "@type" : [ "http://www.w3.org/2002/07/owl#Class" ],
  "http://www.w3.org/2000/01/rdf-schema#comment" : [ {
    "@value" : "Specific subject in a Knowledge Area. This would be \"Distributed Systems\" in the Knowledge Area of \"Mathematics\", or \"Real Analysis\" in the \"Mathematics\" Knowledge Area."
  } ],
  "http://www.w3.org/2000/01/rdf-schema#label" : [ {
    "@value" : "Specific Subject"
  } ],
  "http://www.w3.org/2000/01/rdf-schema#subClassOf" : [ {
    "@id" : "http://precis.rukmal.me/ontology#KnowledgeArea"
  }, {
    "@id" : "_:genid194"
  }, {
    "@id" : "_:genid195"
  } ]
}, {
  "@id" : "http://precis.rukmal.me/ontology#Talk",
  "@type" : [ "http://www.w3.org/2002/07/owl#Class" ],
  "http://www.w3.org/2000/01/rdf-schema#comment" : [ {
    "@value" : "A talk or presentation."
  } ],
  "http://www.w3.org/2000/01/rdf-schema#label" : [ {
    "@value" : "Talk"
  } ],
  "http://www.w3.org/2000/01/rdf-schema#subClassOf" : [ {
    "@id" : "http://precis.rukmal.me/ontology#Portfolio"
  }, {
    "@id" : "_:genid196"
  }, {
    "@id" : "_:genid197"
  } ]
}, {
  "@id" : "http://precis.rukmal.me/ontology#WorkExperience",
  "@type" : [ "http://www.w3.org/2002/07/owl#Class" ],
  "http://www.w3.org/2000/01/rdf-schema#comment" : [ {
    "@value" : "An instance of 'Work Experience'. This would be an internship/assistantship/etc."
  } ],
  "http://www.w3.org/2000/01/rdf-schema#label" : [ {
    "@value" : "Work Experience"
  } ],
  "http://www.w3.org/2000/01/rdf-schema#subClassOf" : [ {
    "@id" : "_:genid198"
  }, {
    "@id" : "_:genid203"
  }, {
    "@id" : "_:genid204"
  }, {
    "@id" : "_:genid205"
  }, {
    "@id" : "_:genid206"
  }, {
    "@id" : "_:genid207"
  }, {
    "@id" : "_:genid208"
  }, {
    "@id" : "_:genid209"
  }, {
    "@id" : "_:genid210"
  } ]
}, {
  "@id" : "http://precis.rukmal.me/ontology#affiliatedWith",
  "@type" : [ "http://www.w3.org/2002/07/owl#ObjectProperty" ],
  "http://www.w3.org/2000/01/rdf-schema#comment" : [ {
    "@value" : "Affiliation for a Portfolio Instance or Accolade Instance. Maps a given instance to an instance of 'Degree' or 'WorkExperience'."
  } ],
  "http://www.w3.org/2000/01/rdf-schema#domain" : [ {
    "@id" : "_:genid1"
  } ],
  "http://www.w3.org/2000/01/rdf-schema#label" : [ {
    "@value" : "Affiliation"
  } ],
  "http://www.w3.org/2000/01/rdf-schema#range" : [ {
    "@id" : "_:genid4"
  } ],
  "http://www.w3.org/2002/07/owl#inverseOf" : [ {
    "@id" : "http://precis.rukmal.me/ontology#hasObject"
  } ]
}, {
  "@id" : "http://precis.rukmal.me/ontology#awardedDegree",
  "@type" : [ "http://www.w3.org/2002/07/owl#ObjectProperty" ],
  "http://www.w3.org/2000/01/rdf-schema#comment" : [ {
    "@value" : "The Degree which was awarded at this organization (should be a pointer to a top-level organization)."
  } ],
  "http://www.w3.org/2000/01/rdf-schema#domain" : [ {
    "@id" : "http://precis.rukmal.me/ontology#Organization"
  } ],
  "http://www.w3.org/2000/01/rdf-schema#label" : [ {
    "@value" : "Degree awarded"
  } ],
  "http://www.w3.org/2000/01/rdf-schema#range" : [ {
    "@id" : "http://precis.rukmal.me/ontology#Degree"
  } ],
  "http://www.w3.org/2002/07/owl#inverseOf" : [ {
    "@id" : "http://precis.rukmal.me/ontology#degreeUniversity"
  } ]
}, {
  "@id" : "http://precis.rukmal.me/ontology#degreeConcentration",
  "@type" : [ "http://www.w3.org/2002/07/owl#DatatypeProperty" ],
  "http://www.w3.org/2000/01/rdf-schema#comment" : [ {
    "@value" : "Concentration of the Degree. For example, \"Finance and Business Economics\", or \"Computational Finance\". This should point to a DBpedia entity corresponding to the Degree being awarded."
  } ],
  "http://www.w3.org/2000/01/rdf-schema#domain" : [ {
    "@id" : "http://precis.rukmal.me/ontology#Degree"
  } ],
  "http://www.w3.org/2000/01/rdf-schema#label" : [ {
    "@value" : "Degree Concentration"
  } ],
  "http://www.w3.org/2000/01/rdf-schema#range" : [ {
    "@id" : "http://www.w3.org/2001/XMLSchema#anyURI"
  } ]
}, {
  "@id" : "http://precis.rukmal.me/ontology#degreeDepartment",
  "@type" : [ "http://www.w3.org/2002/07/owl#ObjectProperty" ],
  "http://www.w3.org/2000/01/rdf-schema#comment" : [ {
    "@value" : "Department awarding the degree (eg: \"Department of Financial Engineering\", or \"Department of Finance and Business Economics\")."
  } ],
  "http://www.w3.org/2000/01/rdf-schema#domain" : [ {
    "@id" : "http://precis.rukmal.me/ontology#Degree"
  } ],
  "http://www.w3.org/2000/01/rdf-schema#label" : [ {
    "@value" : "Department awarding the Degree"
  } ],
  "http://www.w3.org/2000/01/rdf-schema#range" : [ {
    "@id" : "http://precis.rukmal.me/ontology#Organization"
  } ]
}, {
  "@id" : "http://precis.rukmal.me/ontology#degreeGPA",
  "@type" : [ "http://www.w3.org/2002/07/owl#DatatypeProperty" ],
  "http://www.w3.org/2000/01/rdf-schema#comment" : [ {
    "@value" : "Grade (GPA; 4.0 scale) for the Degree (optional for obvious reasons :))."
  } ],
  "http://www.w3.org/2000/01/rdf-schema#domain" : [ {
    "@id" : "http://precis.rukmal.me/ontology#Degree"
  } ],
  "http://www.w3.org/2000/01/rdf-schema#label" : [ {
    "@value" : "Degree GPA (on a 4.0 scale)"
  } ],
  "http://www.w3.org/2000/01/rdf-schema#range" : [ {
    "@id" : "_:genid40"
  } ]
}, {
  "@id" : "http://precis.rukmal.me/ontology#degreeSchool",
  "@type" : [ "http://www.w3.org/2002/07/owl#ObjectProperty" ],
  "http://www.w3.org/2000/01/rdf-schema#comment" : [ {
    "@value" : "The School that awards the degree. For example, this would be the \"Foster School of Business\", or \"College of Arts and Sciences\"."
  } ],
  "http://www.w3.org/2000/01/rdf-schema#domain" : [ {
    "@id" : "http://precis.rukmal.me/ontology#Degree"
  } ],
  "http://www.w3.org/2000/01/rdf-schema#label" : [ {
    "@value" : "School awarding the Degree"
  } ],
  "http://www.w3.org/2000/01/rdf-schema#range" : [ {
    "@id" : "http://precis.rukmal.me/ontology#Organization"
  } ]
}, {
  "@id" : "http://precis.rukmal.me/ontology#degreeType",
  "@type" : [ "http://www.w3.org/2002/07/owl#DatatypeProperty" ],
  "http://www.w3.org/2000/01/rdf-schema#comment" : [ {
    "@value" : "Type of the Degree. For example, \"Bachelor of Arts\", or \"Master of Science\". This should point to a DBpedia entity corresponding to the Degree being awarded."
  } ],
  "http://www.w3.org/2000/01/rdf-schema#domain" : [ {
    "@id" : "http://precis.rukmal.me/ontology#Degree"
  } ],
  "http://www.w3.org/2000/01/rdf-schema#label" : [ {
    "@value" : "Degree Type"
  } ],
  "http://www.w3.org/2000/01/rdf-schema#range" : [ {
    "@id" : "http://www.w3.org/2001/XMLSchema#anyURI"
  } ]
}, {
  "@id" : "http://precis.rukmal.me/ontology#degreeUniversity",
  "@type" : [ "http://www.w3.org/2002/07/owl#ObjectProperty" ],
  "http://www.w3.org/2000/01/rdf-schema#comment" : [ {
    "@value" : "The University (concept: Organization) at which the degree was awarded. This corresponds to the top-level instituion; further object properties exist to specify particular schools/departments. That is, this should point to the organization for the Univesity and not the Department. Eg: awardedAt 'University of Washington'; and should NOT be awardedAt 'Foster School of Business'."
  } ],
  "http://www.w3.org/2000/01/rdf-schema#domain" : [ {
    "@id" : "http://precis.rukmal.me/ontology#Degree"
  } ],
  "http://www.w3.org/2000/01/rdf-schema#label" : [ {
    "@value" : "Organization awarding the Degree"
  } ],
  "http://www.w3.org/2000/01/rdf-schema#range" : [ {
    "@id" : "http://precis.rukmal.me/ontology#Organization"
  } ]
}, {
  "@id" : "http://precis.rukmal.me/ontology#employedAt",
  "@type" : [ "http://www.w3.org/2002/07/owl#ObjectProperty" ],
  "http://www.w3.org/2000/01/rdf-schema#comment" : [ {
    "@value" : "Organization where an instance of Work Experience is taking place."
  } ],
  "http://www.w3.org/2000/01/rdf-schema#domain" : [ {
    "@id" : "http://precis.rukmal.me/ontology#WorkExperience"
  } ],
  "http://www.w3.org/2000/01/rdf-schema#label" : [ {
    "@value" : "Employment Organization"
  } ],
  "http://www.w3.org/2000/01/rdf-schema#range" : [ {
    "@id" : "http://precis.rukmal.me/ontology#Organization"
  } ]
}, {
  "@id" : "http://precis.rukmal.me/ontology#endDate",
  "@type" : [ "http://www.w3.org/2002/07/owl#DatatypeProperty" ],
  "http://www.w3.org/2000/01/rdf-schema#comment" : [ {
    "@value" : "End date of a Instance. When this is included, the 'hasDate' data property corresponds to the start date."
  } ],
  "http://www.w3.org/2000/01/rdf-schema#domain" : [ {
    "@id" : "_:genid45"
  } ],
  "http://www.w3.org/2000/01/rdf-schema#label" : [ {
    "@value" : "endDate"
  } ],
  "http://www.w3.org/2000/01/rdf-schema#range" : [ {
    "@id" : "http://www.w3.org/2001/XMLSchema#dateTime"
  } ]
}, {
  "@id" : "http://precis.rukmal.me/ontology#externalResource",
  "@type" : [ "http://www.w3.org/2002/07/owl#DatatypeProperty" ],
  "http://www.w3.org/2000/01/rdf-schema#comment" : [ {
    "@value" : "Reference to an external resource that describes the same entity. This would typically be a reference to an existing DBpedia concept that describes the same entity. DBpedia references are not directly used here to mitigate the fact that certain user-created entitites will not have existing concepts on DBpedia, and so that we can ensure the existence of some other descriptive fields."
  } ],
  "http://www.w3.org/2000/01/rdf-schema#domain" : [ {
    "@id" : "_:genid50"
  } ],
  "http://www.w3.org/2000/01/rdf-schema#label" : [ {
    "@value" : "External resource"
  } ],
  "http://www.w3.org/2000/01/rdf-schema#range" : [ {
    "@id" : "http://www.w3.org/2001/XMLSchema#anyURI"
  } ]
}, {
  "@id" : "http://precis.rukmal.me/ontology#hasActivity",
  "@type" : [ "http://www.w3.org/2002/07/owl#ObjectProperty" ],
  "http://www.w3.org/2000/01/rdf-schema#comment" : [ {
    "@value" : "An 'Activity' that is a part of an 'ActivityType'."
  } ],
  "http://www.w3.org/2000/01/rdf-schema#domain" : [ {
    "@id" : "http://precis.rukmal.me/ontology#ActivityType"
  } ],
  "http://www.w3.org/2000/01/rdf-schema#label" : [ {
    "@value" : "Constituent Activity"
  } ],
  "http://www.w3.org/2000/01/rdf-schema#range" : [ {
    "@id" : "http://precis.rukmal.me/ontology#Activity"
  } ],
  "http://www.w3.org/2002/07/owl#inverseOf" : [ {
    "@id" : "http://precis.rukmal.me/ontology#inActivityType"
  } ]
}, {
  "@id" : "http://precis.rukmal.me/ontology#hasAuthors",
  "@type" : [ "http://www.w3.org/2002/07/owl#DatatypeProperty" ],
  "http://www.w3.org/2000/01/rdf-schema#comment" : [ {
    "@value" : "List of authors (Human readable for now). This list should mirror the order of authors in the publication. Note that eventually this will be replaced by pointers to individual \"Author\" Classes."
  } ],
  "http://www.w3.org/2000/01/rdf-schema#domain" : [ {
    "@id" : "http://precis.rukmal.me/ontology#Publication"
  } ],
  "http://www.w3.org/2000/01/rdf-schema#label" : [ {
    "@value" : "Author List"
  } ],
  "http://www.w3.org/2000/01/rdf-schema#range" : [ {
    "@id" : "http://www.w3.org/2001/XMLSchema#string"
  } ]
}, {
  "@id" : "http://precis.rukmal.me/ontology#hasChildOrganization",
  "@type" : [ "http://www.w3.org/2002/07/owl#ObjectProperty", "http://www.w3.org/2002/07/owl#TransitiveProperty" ],
  "http://www.w3.org/2000/01/rdf-schema#comment" : [ {
    "@value" : "Child organization pointer, inverse of the 'hasParentOrganization' property."
  } ],
  "http://www.w3.org/2000/01/rdf-schema#domain" : [ {
    "@id" : "http://precis.rukmal.me/ontology#Organization"
  } ],
  "http://www.w3.org/2000/01/rdf-schema#label" : [ {
    "@value" : "Child Organization"
  } ],
  "http://www.w3.org/2000/01/rdf-schema#range" : [ {
    "@id" : "http://precis.rukmal.me/ontology#Organization"
  } ],
  "http://www.w3.org/2002/07/owl#inverseOf" : [ {
    "@id" : "http://precis.rukmal.me/ontology#hasParentOrganization"
  } ]
}, {
  "@id" : "http://precis.rukmal.me/ontology#hasCollaborators",
  "@type" : [ "http://www.w3.org/2002/07/owl#DatatypeProperty" ],
  "http://www.w3.org/2000/01/rdf-schema#comment" : [ {
    "@value" : "List of Collaborators (Human-readable for now). Will eventually change to a mapping to a Person entity."
  } ],
  "http://www.w3.org/2000/01/rdf-schema#domain" : [ {
    "@id" : "http://precis.rukmal.me/ontology#Portfolio"
  } ],
  "http://www.w3.org/2000/01/rdf-schema#label" : [ {
    "@value" : "Collaborators List"
  } ],
  "http://www.w3.org/2000/01/rdf-schema#range" : [ {
    "@id" : "http://www.w3.org/2001/XMLSchema#string"
  } ]
}, {
  "@id" : "http://precis.rukmal.me/ontology#hasCourseCode",
  "@type" : [ "http://www.w3.org/2002/07/owl#DatatypeProperty" ],
  "http://www.w3.org/2000/01/rdf-schema#comment" : [ {
    "@value" : "Code of the course (this would imply that an organization is referenced too). For example: 420, 690, 069, etc."
  } ],
  "http://www.w3.org/2000/01/rdf-schema#domain" : [ {
    "@id" : "http://precis.rukmal.me/ontology#Course"
  } ],
  "http://www.w3.org/2000/01/rdf-schema#label" : [ {
    "@value" : "Course code"
  } ],
  "http://www.w3.org/2000/01/rdf-schema#range" : [ {
    "@id" : "http://www.w3.org/2001/XMLSchema#string"
  } ]
}, {
  "@id" : "http://precis.rukmal.me/ontology#hasDOI",
  "@type" : [ "http://www.w3.org/2002/07/owl#DatatypeProperty" ],
  "http://www.w3.org/2000/01/rdf-schema#comment" : [ {
    "@value" : "Digital Object Identifier (DOI) of the publication. Including this will allow for later expansion if an inference agent is ever added to get more metadata using this."
  } ],
  "http://www.w3.org/2000/01/rdf-schema#domain" : [ {
    "@id" : "http://precis.rukmal.me/ontology#Publication"
  } ],
  "http://www.w3.org/2000/01/rdf-schema#label" : [ {
    "@value" : "Digital Object Identifier (DOI) of the Publication"
  } ],
  "http://www.w3.org/2000/01/rdf-schema#range" : [ {
    "@id" : "http://www.w3.org/2001/XMLSchema#anyURI"
  } ]
}, {
  "@id" : "http://precis.rukmal.me/ontology#hasDate",
  "@type" : [ "http://www.w3.org/2002/07/owl#DatatypeProperty" ],
  "http://www.w3.org/2000/01/rdf-schema#comment" : [ {
    "@value" : "Date of the instance. This implies \"startDate\" when a range is given with \"endDate\"."
  } ],
  "http://www.w3.org/2000/01/rdf-schema#domain" : [ {
    "@id" : "_:genid60"
  } ],
  "http://www.w3.org/2000/01/rdf-schema#label" : [ {
    "@value" : "Date"
  } ],
  "http://www.w3.org/2000/01/rdf-schema#range" : [ {
    "@id" : "http://www.w3.org/2001/XMLSchema#dateTime"
  } ]
}, {
  "@id" : "http://precis.rukmal.me/ontology#hasDepartmentCode",
  "@type" : [ "http://www.w3.org/2002/07/owl#DatatypeProperty" ],
  "http://www.w3.org/2000/01/rdf-schema#comment" : [ {
    "@value" : "Code of the department (this would imply that an organization is referenced too). For example: FIN, CFRM, FE, etc."
  } ],
  "http://www.w3.org/2000/01/rdf-schema#domain" : [ {
    "@id" : "http://precis.rukmal.me/ontology#Course"
  } ],
  "http://www.w3.org/2000/01/rdf-schema#label" : [ {
    "@value" : "Department code"
  } ],
  "http://www.w3.org/2000/01/rdf-schema#range" : [ {
    "@id" : "http://www.w3.org/2001/XMLSchema#string"
  } ]
}, {
  "@id" : "http://precis.rukmal.me/ontology#hasDescription",
  "@type" : [ "http://www.w3.org/2002/07/owl#ObjectProperty" ],
  "http://www.w3.org/2000/01/rdf-schema#comment" : [ {
    "@value" : "Instance of 'Description', which describes the Thing pointing to it."
  } ],
  "http://www.w3.org/2000/01/rdf-schema#domain" : [ {
    "@id" : "_:genid7"
  } ],
  "http://www.w3.org/2000/01/rdf-schema#label" : [ {
    "@value" : "Description"
  } ],
  "http://www.w3.org/2000/01/rdf-schema#range" : [ {
    "@id" : "http://precis.rukmal.me/ontology#Description"
  } ]
}, {
  "@id" : "http://precis.rukmal.me/ontology#hasImage",
  "@type" : [ "http://www.w3.org/2002/07/owl#DatatypeProperty" ],
  "http://www.w3.org/2000/01/rdf-schema#comment" : [ {
    "@value" : "URL to image related to work experience. Can be used when displaying the information at consumption."
  } ],
  "http://www.w3.org/2000/01/rdf-schema#domain" : [ {
    "@id" : "http://precis.rukmal.me/ontology#WorkExperience"
  } ],
  "http://www.w3.org/2000/01/rdf-schema#label" : [ {
    "@value" : "Image"
  } ],
  "http://www.w3.org/2000/01/rdf-schema#range" : [ {
    "@id" : "http://www.w3.org/2001/XMLSchema#anyURI"
  } ]
}, {
  "@id" : "http://precis.rukmal.me/ontology#hasMedia",
  "@type" : [ "http://www.w3.org/2002/07/owl#DatatypeProperty" ],
  "http://www.w3.org/2000/01/rdf-schema#comment" : [ {
    "@value" : "Additional media can be included here. For example, it could link to product/team pages, news articles, etc."
  } ],
  "http://www.w3.org/2000/01/rdf-schema#domain" : [ {
    "@id" : "_:genid67"
  } ],
  "http://www.w3.org/2000/01/rdf-schema#label" : [ {
    "@value" : "Media"
  } ],
  "http://www.w3.org/2000/01/rdf-schema#range" : [ {
    "@id" : "http://www.w3.org/2001/XMLSchema#anyURI"
  } ]
}, {
  "@id" : "http://precis.rukmal.me/ontology#hasName",
  "@type" : [ "http://www.w3.org/2002/07/owl#DatatypeProperty" ],
  "http://www.w3.org/2000/01/rdf-schema#comment" : [ {
    "@value" : "Human readable name for the entity; for display. This is the primary descriptive string for the instance it is mapped to; that is, for 'WorkExperience' it would be the job title, and for 'Publication' it would be the publication title."
  } ],
  "http://www.w3.org/2000/01/rdf-schema#domain" : [ {
    "@id" : "_:genid72"
  } ],
  "http://www.w3.org/2000/01/rdf-schema#label" : [ {
    "@value" : "Human readable name"
  } ],
  "http://www.w3.org/2000/01/rdf-schema#range" : [ {
    "@id" : "http://www.w3.org/2001/XMLSchema#string"
  } ]
}, {
  "@id" : "http://precis.rukmal.me/ontology#hasObject",
  "@type" : [ "http://www.w3.org/2002/07/owl#ObjectProperty" ],
  "http://www.w3.org/2000/01/rdf-schema#comment" : [ {
    "@value" : "Object that was affiliated with the Thing pointing to it. Here, \"Object\" would be typically a 'Portfolio' or 'Accolade' instance, and \"Thing\" would be a 'Degree' or 'WorkExperience' instance."
  } ],
  "http://www.w3.org/2000/01/rdf-schema#domain" : [ {
    "@id" : "_:genid16"
  } ],
  "http://www.w3.org/2000/01/rdf-schema#label" : [ {
    "@value" : "Constituent Object"
  } ],
  "http://www.w3.org/2000/01/rdf-schema#range" : [ {
    "@id" : "_:genid19"
  } ]
}, {
  "@id" : "http://precis.rukmal.me/ontology#hasParentOrganization",
  "@type" : [ "http://www.w3.org/2002/07/owl#ObjectProperty", "http://www.w3.org/2002/07/owl#TransitiveProperty" ],
  "http://www.w3.org/2000/01/rdf-schema#comment" : [ {
    "@value" : "Pointer to a \"parent\" organization instance. For example, the \"Foster School of Business\" hasParentOrganization \"University of Washington\"."
  } ],
  "http://www.w3.org/2000/01/rdf-schema#domain" : [ {
    "@id" : "http://precis.rukmal.me/ontology#Organization"
  } ],
  "http://www.w3.org/2000/01/rdf-schema#label" : [ {
    "@value" : "Parent Organization"
  } ],
  "http://www.w3.org/2000/01/rdf-schema#range" : [ {
    "@id" : "http://precis.rukmal.me/ontology#Organization"
  } ]
}, {
  "@id" : "http://precis.rukmal.me/ontology#hasPriority",
  "@type" : [ "http://www.w3.org/2002/07/owl#DatatypeProperty" ],
  "http://www.w3.org/2000/01/rdf-schema#comment" : [ {
    "@value" : "Priority level of the description (used for deciding truncation in toolkit). This is automatically set to the position of the string in the input \"description\" array of descriptions, when data is loaded using the command line tool."
  } ],
  "http://www.w3.org/2000/01/rdf-schema#domain" : [ {
    "@id" : "http://precis.rukmal.me/ontology#Description"
  } ],
  "http://www.w3.org/2000/01/rdf-schema#label" : [ {
    "@value" : "description priority level"
  } ],
  "http://www.w3.org/2000/01/rdf-schema#range" : [ {
    "@id" : "http://www.w3.org/2001/XMLSchema#nonNegativeInteger"
  } ]
}, {
  "@id" : "http://precis.rukmal.me/ontology#hasSkill",
  "@type" : [ "http://www.w3.org/2002/07/owl#ObjectProperty" ],
  "http://www.w3.org/2000/01/rdf-schema#comment" : [ {
    "@value" : "A skill that is a part of a 'SkillGroup'."
  } ],
  "http://www.w3.org/2000/01/rdf-schema#domain" : [ {
    "@id" : "http://precis.rukmal.me/ontology#SkillGroup"
  } ],
  "http://www.w3.org/2000/01/rdf-schema#label" : [ {
    "@value" : "Constituent Skill"
  } ],
  "http://www.w3.org/2000/01/rdf-schema#range" : [ {
    "@id" : "http://precis.rukmal.me/ontology#Skill"
  } ],
  "http://www.w3.org/2002/07/owl#inverseOf" : [ {
    "@id" : "http://precis.rukmal.me/ontology#inSkillGroup"
  } ]
}, {
  "@id" : "http://precis.rukmal.me/ontology#hasStatus",
  "@type" : [ "http://www.w3.org/2002/07/owl#DatatypeProperty" ],
  "http://www.w3.org/2000/01/rdf-schema#comment" : [ {
    "@value" : "Status of the publication. That is, this property should reflect a paper being \"In Progress\", or \"Under Review\"."
  } ],
  "http://www.w3.org/2000/01/rdf-schema#domain" : [ {
    "@id" : "http://precis.rukmal.me/ontology#Publication"
  } ],
  "http://www.w3.org/2000/01/rdf-schema#label" : [ {
    "@value" : "Publication Status"
  } ],
  "http://www.w3.org/2000/01/rdf-schema#range" : [ {
    "@id" : "http://www.w3.org/2001/XMLSchema#string"
  } ]
}, {
  "@id" : "http://precis.rukmal.me/ontology#hasSubject",
  "@type" : [ "http://www.w3.org/2002/07/owl#ObjectProperty" ],
  "http://www.w3.org/2000/01/rdf-schema#comment" : [ {
    "@value" : "A subject that is a part of a 'KnowledgeArea'."
  } ],
  "http://www.w3.org/2000/01/rdf-schema#domain" : [ {
    "@id" : "http://precis.rukmal.me/ontology#KnowledgeArea"
  } ],
  "http://www.w3.org/2000/01/rdf-schema#label" : [ {
    "@value" : "Constituent Subject"
  } ],
  "http://www.w3.org/2000/01/rdf-schema#range" : [ {
    "@id" : "http://precis.rukmal.me/ontology#Subject"
  } ],
  "http://www.w3.org/2002/07/owl#inverseOf" : [ {
    "@id" : "http://precis.rukmal.me/ontology#inKnowledgeArea"
  } ]
}, {
  "@id" : "http://precis.rukmal.me/ontology#hasText",
  "@type" : [ "http://www.w3.org/2002/07/owl#DatatypeProperty" ],
  "http://www.w3.org/2000/01/rdf-schema#comment" : [ {
    "@value" : "Text of the description. This should be treated as a single \"bullet point\" on a traditional Resume/CV."
  } ],
  "http://www.w3.org/2000/01/rdf-schema#domain" : [ {
    "@id" : "http://precis.rukmal.me/ontology#Description"
  } ],
  "http://www.w3.org/2000/01/rdf-schema#label" : [ {
    "@value" : "description text"
  } ],
  "http://www.w3.org/2000/01/rdf-schema#range" : [ {
    "@id" : "http://www.w3.org/2001/XMLSchema#string"
  } ]
}, {
  "@id" : "http://precis.rukmal.me/ontology#hasWebsite",
  "@type" : [ "http://www.w3.org/2002/07/owl#DatatypeProperty" ],
  "http://www.w3.org/2000/01/rdf-schema#comment" : [ {
    "@value" : "External website of the entity (not used for ontology extension; treat this as user-facing)."
  } ],
  "http://www.w3.org/2000/01/rdf-schema#domain" : [ {
    "@id" : "_:genid82"
  } ],
  "http://www.w3.org/2000/01/rdf-schema#label" : [ {
    "@value" : "Entity website"
  } ],
  "http://www.w3.org/2000/01/rdf-schema#range" : [ {
    "@id" : "http://www.w3.org/2001/XMLSchema#anyURI"
  } ]
}, {
  "@id" : "http://precis.rukmal.me/ontology#inActivityType",
  "@type" : [ "http://www.w3.org/2002/07/owl#ObjectProperty" ],
  "http://www.w3.org/2000/01/rdf-schema#comment" : [ {
    "@value" : "The ActivityType containing the Activity."
  } ],
  "http://www.w3.org/2000/01/rdf-schema#domain" : [ {
    "@id" : "http://precis.rukmal.me/ontology#Activity"
  } ],
  "http://www.w3.org/2000/01/rdf-schema#label" : [ {
    "@value" : "Parent Activity Type"
  } ],
  "http://www.w3.org/2000/01/rdf-schema#range" : [ {
    "@id" : "http://precis.rukmal.me/ontology#ActivityType"
  } ]
}, {
  "@id" : "http://precis.rukmal.me/ontology#inCity",
  "@type" : [ "http://www.w3.org/2002/07/owl#DatatypeProperty" ],
  "http://www.w3.org/2000/01/rdf-schema#comment" : [ {
    "@value" : "The city of the entity."
  } ],
  "http://www.w3.org/2000/01/rdf-schema#domain" : [ {
    "@id" : "_:genid91"
  } ],
  "http://www.w3.org/2000/01/rdf-schema#label" : [ {
    "@value" : "City"
  } ],
  "http://www.w3.org/2000/01/rdf-schema#range" : [ {
    "@id" : "http://www.w3.org/2001/XMLSchema#string"
  } ]
}, {
  "@id" : "http://precis.rukmal.me/ontology#inConferenceOrJournal",
  "@type" : [ "http://www.w3.org/2002/07/owl#DatatypeProperty" ],
  "http://www.w3.org/2000/01/rdf-schema#comment" : [ {
    "@value" : "Conference/Journal name. This will eventually be replaced with a more semantically-correct representation of this information."
  } ],
  "http://www.w3.org/2000/01/rdf-schema#domain" : [ {
    "@id" : "http://precis.rukmal.me/ontology#Publication"
  } ],
  "http://www.w3.org/2000/01/rdf-schema#label" : [ {
    "@value" : "Conference/Journal Name"
  } ],
  "http://www.w3.org/2000/01/rdf-schema#range" : [ {
    "@id" : "http://www.w3.org/2001/XMLSchema#string"
  } ]
}, {
  "@id" : "http://precis.rukmal.me/ontology#inCountry",
  "@type" : [ "http://www.w3.org/2002/07/owl#DatatypeProperty" ],
  "http://www.w3.org/2000/01/rdf-schema#comment" : [ {
    "@value" : "Country of the entity."
  } ],
  "http://www.w3.org/2000/01/rdf-schema#domain" : [ {
    "@id" : "_:genid100"
  } ],
  "http://www.w3.org/2000/01/rdf-schema#label" : [ {
    "@value" : "Country"
  } ],
  "http://www.w3.org/2000/01/rdf-schema#range" : [ {
    "@id" : "http://www.w3.org/2001/XMLSchema#string"
  } ]
}, {
  "@id" : "http://precis.rukmal.me/ontology#inKnowledgeArea",
  "@type" : [ "http://www.w3.org/2002/07/owl#ObjectProperty" ],
  "http://www.w3.org/2000/01/rdf-schema#comment" : [ {
    "@value" : "The knowledge area containing the subject."
  } ],
  "http://www.w3.org/2000/01/rdf-schema#domain" : [ {
    "@id" : "http://precis.rukmal.me/ontology#Subject"
  } ],
  "http://www.w3.org/2000/01/rdf-schema#label" : [ {
    "@value" : "Parent Knowledge Area"
  } ],
  "http://www.w3.org/2000/01/rdf-schema#range" : [ {
    "@id" : "http://precis.rukmal.me/ontology#KnowledgeArea"
  } ]
}, {
  "@id" : "http://precis.rukmal.me/ontology#inPublication",
  "@type" : [ "http://www.w3.org/2002/07/owl#DatatypeProperty" ],
  "http://www.w3.org/2000/01/rdf-schema#comment" : [ {
    "@value" : "Publication name containing the specific publication. As with the other fields in the 'Publication' concept, this will probably be replaced eventually."
  } ],
  "http://www.w3.org/2000/01/rdf-schema#domain" : [ {
    "@id" : "http://precis.rukmal.me/ontology#Publication"
  } ],
  "http://www.w3.org/2000/01/rdf-schema#label" : [ {
    "@value" : "Publication Name"
  } ],
  "http://www.w3.org/2000/01/rdf-schema#range" : [ {
    "@id" : "http://www.w3.org/2001/XMLSchema#string"
  } ]
}, {
  "@id" : "http://precis.rukmal.me/ontology#inSkillGroup",
  "@type" : [ "http://www.w3.org/2002/07/owl#ObjectProperty" ],
  "http://www.w3.org/2000/01/rdf-schema#comment" : [ {
    "@value" : "The SkillGroup containing the Skill."
  } ],
  "http://www.w3.org/2000/01/rdf-schema#domain" : [ {
    "@id" : "http://precis.rukmal.me/ontology#Skill"
  } ],
  "http://www.w3.org/2000/01/rdf-schema#label" : [ {
    "@value" : "Parent SkillGroup"
  } ],
  "http://www.w3.org/2000/01/rdf-schema#range" : [ {
    "@id" : "http://precis.rukmal.me/ontology#SkillGroup"
  } ]
}, {
  "@id" : "http://precis.rukmal.me/ontology#inState",
  "@type" : [ "http://www.w3.org/2002/07/owl#DatatypeProperty" ],
  "http://www.w3.org/2000/01/rdf-schema#comment" : [ {
    "@value" : "State of the entity (United States only)."
  } ],
  "http://www.w3.org/2000/01/rdf-schema#domain" : [ {
    "@id" : "_:genid108"
  } ],
  "http://www.w3.org/2000/01/rdf-schema#label" : [ {
    "@value" : "State"
  } ],
  "http://www.w3.org/2000/01/rdf-schema#range" : [ {
    "@id" : "http://www.w3.org/2001/XMLSchema#string"
  } ]
}, {
  "@id" : "http://precis.rukmal.me/ontology#relatedTo",
  "@type" : [ "http://www.w3.org/2002/07/owl#ObjectProperty", "http://www.w3.org/2002/07/owl#SymmetricProperty", "http://www.w3.org/2002/07/owl#TransitiveProperty" ],
  "http://www.w3.org/2000/01/rdf-schema#comment" : [ {
    "@value" : "A related concept. For example, an instance of 'Award' may have a 'Project', or 'Publication' that it is related to, and vice versa."
  } ],
  "http://www.w3.org/2000/01/rdf-schema#domain" : [ {
    "@id" : "_:genid22"
  } ],
  "http://www.w3.org/2000/01/rdf-schema#label" : [ {
    "@value" : "Related Concept"
  } ],
  "http://www.w3.org/2000/01/rdf-schema#range" : [ {
    "@id" : "_:genid31"
  } ]
}, {
  "@id" : "http://precis.rukmal.me/ontology#taughtAt",
  "@type" : [ "http://www.w3.org/2002/07/owl#ObjectProperty" ],
  "http://www.w3.org/2000/01/rdf-schema#comment" : [ {
    "@value" : "The organization at which the course was taught. This is an optional field, but ideally if this is included, the department and course codes should be too."
  } ],
  "http://www.w3.org/2000/01/rdf-schema#domain" : [ {
    "@id" : "http://precis.rukmal.me/ontology#Course"
  } ],
  "http://www.w3.org/2000/01/rdf-schema#label" : [ {
    "@value" : "Organization which taught the course"
  } ],
  "http://www.w3.org/2000/01/rdf-schema#range" : [ {
    "@id" : "http://precis.rukmal.me/ontology#Organization"
  } ]
}, {
  "@id" : "http://precis.rukmal.me/ontology#withGrade",
  "@type" : [ "http://www.w3.org/2002/07/owl#DatatypeProperty" ],
  "http://www.w3.org/2000/01/rdf-schema#comment" : [ {
    "@value" : "Grade (GPA; 4.0 scale) received in the course (optional for obvious reasons :))."
  } ],
  "http://www.w3.org/2000/01/rdf-schema#domain" : [ {
    "@id" : "http://precis.rukmal.me/ontology#Course"
  } ],
  "http://www.w3.org/2000/01/rdf-schema#label" : [ {
    "@value" : "Course GPA (on a 4.0 scale)"
  } ],
  "http://www.w3.org/2000/01/rdf-schema#range" : [ {
    "@id" : "_:genid117"
  } ]
}, {
  "@id" : "http://purl.org/dc/elements/1.1/abstract",
  "@type" : [ "http://www.w3.org/2002/07/owl#AnnotationProperty" ]
}, {
  "@id" : "http://purl.org/dc/elements/1.1/creator",
  "@type" : [ "http://www.w3.org/2002/07/owl#AnnotationProperty" ]
}, {
  "@id" : "http://purl.org/dc/elements/1.1/title",
  "@type" : [ "http://www.w3.org/2002/07/owl#AnnotationProperty" ]
}, {
  "@id" : "http://purl.org/dc/terms/created",
  "@type" : [ "http://www.w3.org/2002/07/owl#AnnotationProperty" ]
}, {
  "@id" : "http://purl.org/dc/terms/creator",
  "@type" : [ "http://www.w3.org/2002/07/owl#AnnotationProperty" ]
}, {
  "@id" : "http://purl.org/dc/terms/modified",
  "@type" : [ "http://www.w3.org/2002/07/owl#AnnotationProperty" ]
}, {
  "@id" : "http://purl.org/ontology/bibo/doi",
  "@type" : [ "http://www.w3.org/2002/07/owl#AnnotationProperty" ]
}, {
  "@id" : "http://purl.org/vocab/vann/preferredNamespacePrefix",
  "@type" : [ "http://www.w3.org/2002/07/owl#AnnotationProperty" ]
}, {
  "@id" : "http://purl.org/vocab/vann/preferredNamespaceUri",
  "@type" : [ "http://www.w3.org/2002/07/owl#AnnotationProperty" ]
}, {
  "@id" : "http://schema.org/creator",
  "@type" : [ "http://www.w3.org/2002/07/owl#AnnotationProperty" ]
}, {
  "@id" : "http://schema.org/description",
  "@type" : [ "http://www.w3.org/2002/07/owl#AnnotationProperty" ]
}, {
  "@id" : "http://schema.org/license",
  "@type" : [ "http://www.w3.org/2002/07/owl#AnnotationProperty" ]
}, {
  "@id" : "http://www.w3.org/2001/XMLSchema#gMonth",
  "@type" : [ "http://www.w3.org/2000/01/rdf-schema#Datatype" ]
}, {
  "@id" : "http://www.w3.org/2001/XMLSchema#gYear",
  "@type" : [ "http://www.w3.org/2000/01/rdf-schema#Datatype" ]
}, {
  "@id" : "http://www.w3.org/2002/07/owl#priorVersion",
  "@type" : [ "http://www.w3.org/2002/07/owl#AnnotationProperty" ]
} ]